{
  "title": "That Time I Was Blackmailed by the Class’s Green Tea Bitch",
  "author": "Xian Jun",
  "artist": "Xian Jun",
  "description": "Após o término da aula, uma aluna de honra é ameaçada pela Vadia do Chá Verde da turma. “Eu nunca pensei que uma garota certinha faria algo assim.” “Se você não quiser que eu exponha o seu segredo vergonhoso, você deve…” Um romance fofo que se origina de um mal-entendido começa no momento em que fui chantageada pela vadia do chá verde da classe!",
  "cover": "https://images2.imgbox.com/20/ed/2ylAD2RN_o.jpg",
  "status": "Em lançamento",
  "chapters": {
    "59": {
      "title": "Capítulo 59 - A culpa de TongTong",
      "groups": {
        "Valkyriescan": [
          "https://images2.imgbox.com/5d/1a/FIx6cbpq_o.jpg",
          "https://images2.imgbox.com/d7/e4/jWYRqEhU_o.jpg",
          "https://images2.imgbox.com/57/9a/knMtHJKN_o.jpg",
          "https://images2.imgbox.com/db/60/btN9528B_o.jpg",
          "https://images2.imgbox.com/e6/3c/Q8nndShV_o.jpg",
          "https://images2.imgbox.com/cd/ab/UyU4sWxB_o.jpg",
          "https://images2.imgbox.com/8b/e4/MyQvx6cP_o.jpg",
          "https://images2.imgbox.com/f4/92/iyldwySb_o.jpg",
          "https://images2.imgbox.com/6f/13/SvsVL8TY_o.jpg",
          "https://images2.imgbox.com/a2/75/7iZZeGla_o.jpg",
          "https://images2.imgbox.com/5a/a4/mQM6XEjl_o.jpg"
        ]
      }
    },
    "58": {
      "title": "Capítulo 58 - Deixa eu cuidar de você",
      "groups": {
        "Valkyriescan": [
          "https://images2.imgbox.com/ce/be/biY0WTVf_o.jpg",
          "https://images2.imgbox.com/04/18/H9eTVJOU_o.jpg",
          "https://images2.imgbox.com/cf/00/4LUbDutX_o.jpg",
          "https://images2.imgbox.com/f5/61/RdoupwkE_o.jpg",
          "https://images2.imgbox.com/ce/ec/52LXG05b_o.jpg",
          "https://images2.imgbox.com/f8/31/2PGt7BoY_o.jpg",
          "https://images2.imgbox.com/09/25/vptixCty_o.jpg",
          "https://images2.imgbox.com/7f/51/YsclPs7c_o.jpg",
          "https://images2.imgbox.com/d4/9e/tG8wLdet_o.jpg",
          "https://images2.imgbox.com/ac/87/TFnhe1xS_o.jpg",
          "https://images2.imgbox.com/73/97/Z959pEfA_o.jpg"
        ]
      }
    },
    "57": {
      "title": "Capítulo 57 - Presente da mamãe",
      "groups": {
        "Valkyriescan": [
          "https://images2.imgbox.com/48/6e/dtr48wEj_o.jpg",
          "https://images2.imgbox.com/c1/23/42pCVPqD_o.jpg",
          "https://images2.imgbox.com/a4/1b/jaGEFRML_o.jpg",
          "https://images2.imgbox.com/e7/00/CS4XBEal_o.jpg",
          "https://images2.imgbox.com/9c/cf/001KBTTs_o.jpg",
          "https://images2.imgbox.com/11/10/TNM0RPJ8_o.jpg",
          "https://images2.imgbox.com/7c/a0/vw3Jh7xb_o.jpg",
          "https://images2.imgbox.com/fe/60/i8xdoLm0_o.jpg",
          "https://images2.imgbox.com/2b/4f/jveZKfFv_o.jpg",
          "https://images2.imgbox.com/ce/9b/NydOOSBk_o.jpg",
          "https://images2.imgbox.com/7c/50/vV4bd4oC_o.jpg"
        ]
      }
    },
    "56": {
      "title": "Capítulo 56 - Talvez eu possa ser capaz de aceitar isso",
      "groups": {
        "Valkyriescan": [
          "https://images2.imgbox.com/bb/01/L02JefJQ_o.jpg",
          "https://images2.imgbox.com/21/be/f8YlvFgp_o.jpg",
          "https://images2.imgbox.com/2a/68/0Xx2bQKX_o.jpg",
          "https://images2.imgbox.com/9f/52/BBsxRD5C_o.jpg",
          "https://images2.imgbox.com/6a/c9/2kfQLJs4_o.jpg",
          "https://images2.imgbox.com/f3/cc/WdAHPMfS_o.jpg",
          "https://images2.imgbox.com/3a/59/kTS6m2qT_o.jpg",
          "https://images2.imgbox.com/d3/cb/g91At7MZ_o.jpg",
          "https://images2.imgbox.com/58/9b/Jyoqlexp_o.jpg",
          "https://images2.imgbox.com/35/5a/q4lPFann_o.jpg",
          "https://images2.imgbox.com/9f/1c/9KkaddkE_o.jpg",
          "https://images2.imgbox.com/41/0c/PPuLPjvu_o.jpg",
          "https://images2.imgbox.com/fe/12/yRc0zqWQ_o.jpg",
          "https://images2.imgbox.com/db/cd/ojEF7rkM_o.jpg",
          "https://images2.imgbox.com/cd/62/OtYXjRcz_o.jpg",
          "https://images2.imgbox.com/b2/ca/twhGO8pu_o.jpg",
          "https://images2.imgbox.com/d1/42/KkmBPX45_o.jpg",
          "https://images2.imgbox.com/7d/98/ynzS91ck_o.jpg",
          "https://images2.imgbox.com/46/6a/zKRkPNbT_o.jpg",
          "https://images2.imgbox.com/6c/73/sKQT9eIj_o.jpg",
          "https://images2.imgbox.com/01/4f/G8Nbo7YR_o.jpg",
          "https://images2.imgbox.com/5d/14/SndmHLkW_o.jpg",
          "https://images2.imgbox.com/11/7e/nAf7KI4T_o.jpg",
          "https://images2.imgbox.com/6e/ec/h6978iCi_o.jpg",
          "https://images2.imgbox.com/89/aa/mrLLEpgf_o.jpg",
          "https://images2.imgbox.com/9e/81/az2oe3eM_o.jpg"
        ]
      }
    },
    "55": {
      "title": "Capítulo 55 - O motivo real do sofrimento",
      "groups": {
        "Valkyriescan": [
          "https://images2.imgbox.com/de/17/SEbtXkPi_o.jpg",
          "https://images2.imgbox.com/3f/39/B3v7dthq_o.jpg",
          "https://images2.imgbox.com/ab/fb/0Nvaed4V_o.jpg",
          "https://images2.imgbox.com/d5/35/iCdIfzYs_o.jpg",
          "https://images2.imgbox.com/8a/0a/zrDUBkVx_o.jpg",
          "https://images2.imgbox.com/4e/58/nOe5kMYe_o.jpg",
          "https://images2.imgbox.com/82/c4/CYaEffSg_o.jpg",
          "https://images2.imgbox.com/66/0b/m72hD0CK_o.jpg",
          "https://images2.imgbox.com/f6/96/yzCUfptz_o.jpg",
          "https://images2.imgbox.com/15/7f/KlYXE5ab_o.jpg",
          "https://images2.imgbox.com/41/c8/f2M17eS6_o.jpg",
          "https://images2.imgbox.com/da/11/tRgoCuPn_o.jpg",
          "https://images2.imgbox.com/e8/4b/4dEkWAL6_o.jpg",
          "https://images2.imgbox.com/9a/42/GHct19dy_o.jpg",
          "https://images2.imgbox.com/c7/96/0ZoIp1xy_o.jpg",
          "https://images2.imgbox.com/2b/27/RrvAWYw5_o.jpg",
          "https://images2.imgbox.com/f3/4c/N3qz4KRt_o.jpg",
          "https://images2.imgbox.com/56/97/AUFLnwDL_o.jpg",
          "https://images2.imgbox.com/a0/d4/kUCkj9us_o.jpg",
          "https://images2.imgbox.com/5e/38/zCTv9Ntn_o.jpg",
          "https://images2.imgbox.com/d2/d6/ChghA8Dp_o.jpg",
          "https://images2.imgbox.com/b4/3d/xDdQdIqQ_o.jpg",
          "https://images2.imgbox.com/80/2a/ROboWerv_o.jpg",
          "https://images2.imgbox.com/e9/bb/jmwj7dyR_o.jpg",
          "https://images2.imgbox.com/e7/67/DObCQLUb_o.jpg",
          "https://images2.imgbox.com/da/3f/gvjYbGUp_o.jpg"
        ]
      }
    },
    "54": {
      "title": "Capítulo 54 - Obrigada… Pelo doce…",
      "groups": {
        "Valkyriescan": [
          "https://images2.imgbox.com/57/5f/3kfVHUIs_o.jpg",
          "https://images2.imgbox.com/02/ef/sv8s0Xiq_o.jpg",
          "https://images2.imgbox.com/5a/ab/bROS5QpZ_o.jpg",
          "https://images2.imgbox.com/e5/2a/Lm9Qqa8M_o.jpg",
          "https://images2.imgbox.com/6d/aa/ybaUPSQp_o.jpg",
          "https://images2.imgbox.com/1a/de/dzBuadIx_o.jpg",
          "https://images2.imgbox.com/a6/77/SZs4eNMN_o.jpg",
          "https://images2.imgbox.com/cc/34/3sr9uV2x_o.jpg",
          "https://images2.imgbox.com/9c/a3/eu1wvj1y_o.jpg",
          "https://images2.imgbox.com/7a/af/Mk0CD8nJ_o.jpg",
          "https://images2.imgbox.com/4b/5f/5r721s6z_o.jpg",
          "https://images2.imgbox.com/aa/0a/4djcme8s_o.jpg",
          "https://images2.imgbox.com/ea/f3/90OyPa38_o.jpg",
          "https://images2.imgbox.com/1c/67/URwKWFXw_o.jpg",
          "https://images2.imgbox.com/9d/dd/nxTlgUnR_o.jpg",
          "https://images2.imgbox.com/fb/66/AegZgTth_o.jpg",
          "https://images2.imgbox.com/ef/5e/dIcSvpMU_o.jpg",
          "https://images2.imgbox.com/54/4f/Eaciessq_o.jpg",
          "https://images2.imgbox.com/a5/42/f6f2JlNP_o.jpg",
          "https://images2.imgbox.com/86/2f/iC7VSx27_o.jpg",
          "https://images2.imgbox.com/15/d4/w0O52xUd_o.jpg",
          "https://images2.imgbox.com/cc/6c/k2FiSUo0_o.jpg",
          "https://images2.imgbox.com/58/b1/qqbjycPo_o.jpg",
          "https://images2.imgbox.com/35/a6/gCjuq0Ge_o.jpg",
          "https://images2.imgbox.com/4e/6b/i10PwUrc_o.jpg",
          "https://images2.imgbox.com/07/ca/se65c8Nt_o.jpg"
        ]
      }
    },
    "53": {
      "title": "Capítulo 53 - Briga",
      "groups": {
        "Valkyriescan": [
          "https://images2.imgbox.com/1e/53/ObmzyBUE_o.jpg",
          "https://images2.imgbox.com/fc/41/5SWsavUA_o.jpg",
          "https://images2.imgbox.com/f1/a3/PDnWhi25_o.jpg",
          "https://images2.imgbox.com/74/e1/zEVrn9A7_o.jpg",
          "https://images2.imgbox.com/7f/e1/pIZvfalw_o.jpg",
          "https://images2.imgbox.com/61/65/oLSrwZ7B_o.jpg",
          "https://images2.imgbox.com/11/b4/DKNnbWwy_o.jpg",
          "https://images2.imgbox.com/dc/19/76HtS8eS_o.jpg",
          "https://images2.imgbox.com/70/b0/xzsgXCUu_o.jpg",
          "https://images2.imgbox.com/75/e7/7MKnbxnr_o.jpg",
          "https://images2.imgbox.com/c1/33/OvF3O3BQ_o.jpg",
          "https://images2.imgbox.com/56/db/PNBm6Lxs_o.jpg",
          "https://images2.imgbox.com/30/09/iYwqmtln_o.jpg",
          "https://images2.imgbox.com/10/ee/femozzmB_o.jpg",
          "https://images2.imgbox.com/b9/35/gASPOmHb_o.jpg",
          "https://images2.imgbox.com/2b/d7/3DwhoKTp_o.jpg",
          "https://images2.imgbox.com/2b/67/zsBVIHHR_o.jpg",
          "https://images2.imgbox.com/6e/38/ge7zrMTr_o.jpg",
          "https://images2.imgbox.com/9a/dd/DUKhho9T_o.jpg",
          "https://images2.imgbox.com/7d/ad/OEnDUpxK_o.jpg",
          "https://images2.imgbox.com/54/f4/gmUl8klw_o.jpg",
          "https://images2.imgbox.com/9f/7c/UQBGD2Nc_o.jpg",
          "https://images2.imgbox.com/9f/18/DjoCQwBo_o.jpg",
          "https://images2.imgbox.com/2b/a2/mdQ9vhHK_o.jpg",
          "https://images2.imgbox.com/eb/52/piI8b7vz_o.jpg",
          "https://images2.imgbox.com/a4/5c/J6yQchVd_o.jpg"
        ]
      }
    },
    "52": {
      "title": "Capítulo 52 - A queda de uma dominadora???",
      "groups": {
        "Valkyriescan": [
          "https://images2.imgbox.com/12/a0/NCPVf0jU_o.jpg",
          "https://images2.imgbox.com/9f/84/EbymRiGq_o.jpg",
          "https://images2.imgbox.com/70/ae/Rd9vuvjL_o.jpg",
          "https://images2.imgbox.com/d1/52/E3X5XCb3_o.jpg",
          "https://images2.imgbox.com/ba/b7/9Azr9R3T_o.jpg",
          "https://images2.imgbox.com/50/ea/2ylfWsPR_o.jpg",
          "https://images2.imgbox.com/02/e2/cc2OBr0V_o.jpg",
          "https://images2.imgbox.com/68/cf/LMLud6VA_o.jpg",
          "https://images2.imgbox.com/5e/80/W20yPAbX_o.jpg",
          "https://images2.imgbox.com/61/4d/Sefa7QBY_o.jpg",
          "https://images2.imgbox.com/ca/d8/yEJPljoK_o.jpg",
          "https://images2.imgbox.com/ee/7d/zP2eyWAz_o.jpg",
          "https://images2.imgbox.com/eb/5f/ktBISJY0_o.jpg",
          "https://images2.imgbox.com/51/e7/chRvUKdN_o.jpg",
          "https://images2.imgbox.com/34/cc/Wv0HXI7G_o.jpg",
          "https://images2.imgbox.com/61/6b/CRY5LkpT_o.jpg",
          "https://images2.imgbox.com/b5/25/2498FKSW_o.jpg",
          "https://images2.imgbox.com/74/8b/Jwq6N6zK_o.jpg",
          "https://images2.imgbox.com/de/65/wsd2SwtZ_o.jpg",
          "https://images2.imgbox.com/91/91/KJCmqpO2_o.jpg",
          "https://images2.imgbox.com/87/51/lPhNCtx7_o.jpg",
          "https://images2.imgbox.com/06/0a/21LaGzXN_o.jpg",
          "https://images2.imgbox.com/87/f6/UD4uZsa3_o.jpg",
          "https://images2.imgbox.com/46/64/6uD6S6rb_o.jpg",
          "https://images2.imgbox.com/e7/14/QyoX7V0z_o.jpg"
        ]
      }
    },
    "51": {
      "title": "Capítulo 51 - Vá com calma",
      "groups": {
        "Valkyriescan": [
          "https://images2.imgbox.com/1b/c5/NY29zpYQ_o.jpg",
          "https://images2.imgbox.com/6e/b0/wnPRjr8L_o.jpg",
          "https://images2.imgbox.com/47/ee/vqpOfAkX_o.jpg",
          "https://images2.imgbox.com/64/67/DpqLByg4_o.jpg",
          "https://images2.imgbox.com/f5/e4/bCn5Ar4B_o.jpg",
          "https://images2.imgbox.com/de/47/i8okB9tl_o.jpg",
          "https://images2.imgbox.com/fe/5d/nYtb8AWu_o.jpg",
          "https://images2.imgbox.com/13/59/UHjAhIg4_o.jpg",
          "https://images2.imgbox.com/3b/af/U87XYAl1_o.jpg",
          "https://images2.imgbox.com/1f/0a/t6EVQpoB_o.jpg",
          "https://images2.imgbox.com/2e/0d/dSkJl1Bu_o.jpg"
        ]
      }
    },
    "50": {
      "title": "Capítulo 50 - Dê um tempo difícil",
      "groups": {
        "Valkyriescan": [
          "https://images2.imgbox.com/f2/e3/h9CjV8f3_o.jpg",
          "https://images2.imgbox.com/92/62/MkbMNkHR_o.jpg",
          "https://images2.imgbox.com/ff/fb/iIPZmTJu_o.jpg",
          "https://images2.imgbox.com/9d/a8/mEedDa1u_o.jpg",
          "https://images2.imgbox.com/3b/d6/XHaiTlDA_o.jpg",
          "https://images2.imgbox.com/50/3c/sV8MQkF4_o.jpg",
          "https://images2.imgbox.com/59/0b/PG8IMYaC_o.jpg",
          "https://images2.imgbox.com/5e/b3/cfnzCMqw_o.jpg",
          "https://images2.imgbox.com/1c/2f/NVNkPshu_o.jpg",
          "https://images2.imgbox.com/d1/dd/CW1SzSe5_o.jpg",
          "https://images2.imgbox.com/f6/78/PoUInGbG_o.jpg"
        ]
      }
    },
    "49": {
      "title": "Capítulo 49 - Progresso",
      "groups": {
        "Valkyriescan": [
          "https://images2.imgbox.com/d6/bf/CaTUftAR_o.jpg",
          "https://images2.imgbox.com/e9/28/tgBJ4oX2_o.jpg",
          "https://images2.imgbox.com/69/05/Wlv6S68T_o.jpg",
          "https://images2.imgbox.com/c1/f5/Mk1V6MJa_o.jpg",
          "https://images2.imgbox.com/fc/58/IvJvfxom_o.jpg",
          "https://images2.imgbox.com/6b/e8/Jl0eUqG1_o.jpg",
          "https://images2.imgbox.com/5e/40/lZeoivko_o.jpg",
          "https://images2.imgbox.com/9b/5e/EPdfZFY7_o.jpg",
          "https://images2.imgbox.com/da/5f/AI2wL2z2_o.jpg",
          "https://images2.imgbox.com/eb/8b/YRmQwTru_o.jpg",
          "https://images2.imgbox.com/36/c7/5iUnYHES_o.jpg"
        ]
      }
    },
    "48": {
      "title": "Capítulo 48 - Paciência e compostura",
      "groups": {
        "Valkyriescan": [
          "https://images2.imgbox.com/ce/26/zf6hsQcg_o.jpg",
          "https://images2.imgbox.com/72/82/vvnBpEcY_o.jpg",
          "https://images2.imgbox.com/ea/fa/gOT5jDtj_o.jpg",
          "https://images2.imgbox.com/14/64/tOVz49kT_o.jpg",
          "https://images2.imgbox.com/c8/4d/kr15xBTD_o.jpg",
          "https://images2.imgbox.com/22/b4/ECMbpfwy_o.jpg",
          "https://images2.imgbox.com/53/6c/833I00xX_o.jpg",
          "https://images2.imgbox.com/5a/5b/xGHmfXO7_o.jpg",
          "https://images2.imgbox.com/7d/55/0PlejuA4_o.jpg",
          "https://images2.imgbox.com/71/b8/fKemTlJb_o.jpg",
          "https://images2.imgbox.com/6f/f5/V0oP0UP2_o.jpg"
        ]
      }
    },
    "47": {
      "title": "Capítulo 47 - Tá rolando alguma coisa",
      "groups": {
        "Valkyriescan": [
          "https://images2.imgbox.com/a0/d8/ShKvvU77_o.jpg",
          "https://images2.imgbox.com/0b/55/2cKFchaM_o.jpg",
          "https://images2.imgbox.com/17/db/mFrF7784_o.jpg",
          "https://images2.imgbox.com/88/ba/yxQGcBtn_o.jpg",
          "https://images2.imgbox.com/16/67/2LEer270_o.jpg",
          "https://images2.imgbox.com/5a/48/krnM0C2p_o.jpg",
          "https://images2.imgbox.com/63/fb/V95fFaZ7_o.jpg",
          "https://images2.imgbox.com/e2/90/ODyCr9xO_o.jpg",
          "https://images2.imgbox.com/b3/be/CeYc9wAs_o.jpg",
          "https://images2.imgbox.com/e8/fa/esDrkNuc_o.jpg",
          "https://images2.imgbox.com/e3/4f/VARQe9GP_o.jpg"
        ]
      }
    },
    "46": {
      "title": "Capítulo 46 - Não é perfeito?",
      "groups": {
        "Valkyriescan": [
          "https://images2.imgbox.com/c3/05/VVNAOyYQ_o.jpg",
          "https://images2.imgbox.com/0f/24/bEou9DXK_o.jpg",
          "https://images2.imgbox.com/94/7b/SlPRwfi8_o.jpg",
          "https://images2.imgbox.com/03/45/n8sysD7k_o.jpg",
          "https://images2.imgbox.com/d8/a8/ejOdej9q_o.jpg",
          "https://images2.imgbox.com/12/59/2wXzE8Tm_o.jpg",
          "https://images2.imgbox.com/6f/d2/03AuMHMs_o.jpg",
          "https://images2.imgbox.com/17/62/HIsWHWYa_o.jpg",
          "https://images2.imgbox.com/85/a7/q78e9YXz_o.jpg",
          "https://images2.imgbox.com/2c/fc/bUu3hLDm_o.jpg",
          "https://images2.imgbox.com/03/79/y0ELePt6_o.jpg",
          "https://images2.imgbox.com/f0/07/5ORk5YaF_o.jpg",
          "https://images2.imgbox.com/91/e4/t5d4Kxb1_o.jpg",
          "https://images2.imgbox.com/e9/f4/wyijQkSW_o.jpg",
          "https://images2.imgbox.com/06/7d/yH0sKOBE_o.jpg",
          "https://images2.imgbox.com/c3/8d/ZUrDrjJp_o.jpg",
          "https://images2.imgbox.com/24/e6/71O2QFwX_o.jpg",
          "https://images2.imgbox.com/09/5a/77C8OWK0_o.jpg",
          "https://images2.imgbox.com/af/68/DoO8In2P_o.jpg",
          "https://images2.imgbox.com/d3/05/8i83W6eB_o.jpg",
          "https://images2.imgbox.com/c3/44/VZTKanW2_o.jpg"
        ]
      }
    },
    "45": {
      "title": "Capítulo 45 - É disso que você gosta?",
      "groups": {
        "Valkyriescan": [
          "https://images2.imgbox.com/84/3c/xkKMNumJ_o.jpg",
          "https://images2.imgbox.com/fd/af/0rVzUtDr_o.jpg",
          "https://images2.imgbox.com/cb/8a/pIkLZ9x7_o.jpg",
          "https://images2.imgbox.com/60/d7/0oc2xdpD_o.jpg",
          "https://images2.imgbox.com/4e/03/SHMkAPku_o.jpg",
          "https://images2.imgbox.com/ef/fb/QUamOjDy_o.jpg",
          "https://images2.imgbox.com/03/c1/hj7gy1JG_o.jpg",
          "https://images2.imgbox.com/2d/57/eaTJyPoR_o.jpg",
          "https://images2.imgbox.com/c6/c1/flCwcrzX_o.jpg",
          "https://images2.imgbox.com/0a/f6/qz7R8w82_o.jpg",
          "https://images2.imgbox.com/84/ba/RItJWYyl_o.jpg",
          "https://images2.imgbox.com/bc/8e/ajDV8nDq_o.jpg",
          "https://images2.imgbox.com/1a/53/nXBqTC5M_o.jpg",
          "https://images2.imgbox.com/db/b5/MKbQV2ol_o.jpg",
          "https://images2.imgbox.com/98/39/5Iaw7BoF_o.jpg",
          "https://images2.imgbox.com/92/74/G8ecYoIX_o.jpg",
          "https://images2.imgbox.com/47/26/odSW3Vyy_o.jpg",
          "https://images2.imgbox.com/54/05/73ZcHBlM_o.jpg",
          "https://images2.imgbox.com/51/2f/SlIHfu8M_o.jpg",
          "https://images2.imgbox.com/37/56/UZYlCLjv_o.jpg",
          "https://images2.imgbox.com/82/45/YovXxL8b_o.jpg"
        ]
      }
    },
    "44": {
      "title": "Capítulo 44 - Você não está me devendo nenhuma explicação?",
      "groups": {
        "Valkyriescan": [
          "https://images2.imgbox.com/85/aa/HNeUij2m_o.jpg",
          "https://images2.imgbox.com/db/0a/tXKdDbni_o.jpg",
          "https://images2.imgbox.com/1d/b8/DbHOY5CY_o.jpg",
          "https://images2.imgbox.com/28/c9/YAjyNGXB_o.jpg",
          "https://images2.imgbox.com/a8/60/PtH4kiFS_o.jpg",
          "https://images2.imgbox.com/b6/a5/LvSJiTgn_o.jpg",
          "https://images2.imgbox.com/3c/d5/FCu416Ok_o.jpg",
          "https://images2.imgbox.com/fb/31/7I4MHCNz_o.jpg",
          "https://images2.imgbox.com/24/ad/xVT8SIJC_o.jpg",
          "https://images2.imgbox.com/a1/c0/o6o6Y95t_o.jpg",
          "https://images2.imgbox.com/6e/24/5BSA6509_o.jpg"
        ]
      }
    },
    "43": {
      "title": "Capítulo 43 - Mais próxima",
      "groups": {
        "Valkyriescan": [
          "https://images2.imgbox.com/f4/9a/r6eKYCbd_o.jpg",
          "https://images2.imgbox.com/ee/21/ItXr4kiG_o.jpg",
          "https://images2.imgbox.com/fa/3d/20V8FyDi_o.jpg",
          "https://images2.imgbox.com/55/d9/T4R7f84Y_o.jpg",
          "https://images2.imgbox.com/b3/c3/fC83cxxm_o.jpg",
          "https://images2.imgbox.com/bd/e0/fEo2xxVI_o.jpg",
          "https://images2.imgbox.com/f6/df/IUTYhUnA_o.jpg",
          "https://images2.imgbox.com/1a/94/M0wY95Te_o.jpg",
          "https://images2.imgbox.com/8a/06/MSCsiKDJ_o.jpg",
          "https://images2.imgbox.com/9a/b2/HXxCYPiX_o.jpg",
          "https://images2.imgbox.com/23/81/qyWOtrJZ_o.jpg"
        ]
      }
    },
    "42": {
      "title": "Capítulo 42 - Fazer as pazes?",
      "groups": {
        "Valkyriescan": [
          "https://images2.imgbox.com/5f/8e/twu9rpqB_o.jpg",
          "https://images2.imgbox.com/e9/c6/0SIGsjR0_o.jpg",
          "https://images2.imgbox.com/bd/8f/vtqV8WoI_o.jpg",
          "https://images2.imgbox.com/77/03/b1jcm1ol_o.jpg",
          "https://images2.imgbox.com/47/76/w82ZGes2_o.jpg",
          "https://images2.imgbox.com/93/38/qUqWqkBx_o.jpg",
          "https://images2.imgbox.com/97/c6/qxPVT8mg_o.jpg",
          "https://images2.imgbox.com/6e/55/GmNGfY92_o.jpg",
          "https://images2.imgbox.com/4c/5c/Olrkz9Cn_o.jpg",
          "https://images2.imgbox.com/83/0c/Nc06UBHY_o.jpg",
          "https://images2.imgbox.com/30/f8/pZ5tturB_o.jpg"
        ]
      }
    },
    "41": {
      "title": "Capítulo 41 - Quem está brava?",
      "groups": {
        "Valkyriescan": [
          "https://images2.imgbox.com/50/8a/Cul5PRLW_o.jpg",
          "https://images2.imgbox.com/37/dc/z9p0ywkO_o.jpg",
          "https://images2.imgbox.com/8a/3b/qz0uOjtJ_o.jpg",
          "https://images2.imgbox.com/b1/25/FpWsQm0v_o.jpg",
          "https://images2.imgbox.com/89/a8/ApjPql42_o.jpg",
          "https://images2.imgbox.com/4f/f0/92QSTvAL_o.jpg",
          "https://images2.imgbox.com/6f/b4/u8anSXVS_o.jpg",
          "https://images2.imgbox.com/67/6d/tkO4zmYq_o.jpg",
          "https://images2.imgbox.com/30/7a/Wk5bO9He_o.jpg",
          "https://images2.imgbox.com/be/be/wyP7zzsm_o.jpg",
          "https://images2.imgbox.com/84/82/YZTurStf_o.jpg"
        ]
      }
    },
    "40": {
      "title": "Capítulo 40 - Eu gostei disso",
      "groups": {
        "Valkyriescan": [
          "https://images2.imgbox.com/17/ba/JCxWJqfu_o.jpg",
          "https://images2.imgbox.com/61/e6/tL3ekcak_o.jpg",
          "https://images2.imgbox.com/f3/9c/Rht0zZZE_o.jpg",
          "https://images2.imgbox.com/8b/3a/9rOOtWD8_o.jpg",
          "https://images2.imgbox.com/b9/9a/FL3ODCU3_o.jpg",
          "https://images2.imgbox.com/9f/98/ZlCSdyIW_o.jpg",
          "https://images2.imgbox.com/e2/45/5qb3hohi_o.jpg",
          "https://images2.imgbox.com/64/80/9qj3haiX_o.jpg",
          "https://images2.imgbox.com/0a/89/nIlJSiR5_o.jpg",
          "https://images2.imgbox.com/45/6b/8T3LPwOk_o.jpg",
          "https://images2.imgbox.com/aa/8b/Tk1H325a_o.jpg"
        ]
      }
    },
    "39": {
      "title": "Capítulo 39 - Bai Yen",
      "groups": {
        "Valkyriescan": [
          "https://images2.imgbox.com/53/6e/4Kd24qKT_o.jpg",
          "https://images2.imgbox.com/bf/13/0rjXfhFP_o.jpg",
          "https://images2.imgbox.com/fa/81/IZx8XeFd_o.jpg",
          "https://images2.imgbox.com/e8/2b/05Vn5gzR_o.jpg",
          "https://images2.imgbox.com/29/4f/tXaxuo9B_o.jpg",
          "https://images2.imgbox.com/d5/2f/B5mtmVpj_o.jpg",
          "https://images2.imgbox.com/4b/bc/uqLj1sln_o.jpg",
          "https://images2.imgbox.com/c0/3a/NAMqzprE_o.jpg",
          "https://images2.imgbox.com/d2/f8/etOR22ZD_o.jpg",
          "https://images2.imgbox.com/d0/18/xv9TS7tp_o.jpg",
          "https://images2.imgbox.com/b1/b4/mN1clBzq_o.jpg"
        ]
      }
    },
    "38": {
      "title": "Capítulo 38 - Pequenos problemas?",
      "groups": {
        "Valkyriescan": [
          "https://images2.imgbox.com/2f/0f/ZU40VHXb_o.jpg",
          "https://images2.imgbox.com/81/79/mNcNHG2g_o.jpg",
          "https://images2.imgbox.com/1b/89/u7xjk0q7_o.jpg",
          "https://images2.imgbox.com/b2/0d/aGz8L9CK_o.jpg",
          "https://images2.imgbox.com/e6/0e/2bZHuR3o_o.jpg",
          "https://images2.imgbox.com/08/3f/ITrrj35P_o.jpg",
          "https://images2.imgbox.com/56/6c/jyqQ3RWD_o.jpg",
          "https://images2.imgbox.com/92/f2/1kdBa8M4_o.jpg",
          "https://images2.imgbox.com/13/bc/YMgPUjdU_o.jpg",
          "https://images2.imgbox.com/3f/ce/j12Wmyfe_o.jpg",
          "https://images2.imgbox.com/bf/4a/aJcSCa23_o.jpg"
        ]
      }
    },
    "37.2": {
      "title": "Capítulo 37.2 - Extra do cotidiano",
      "groups": {
        "Valkyriescan": [
          "https://images2.imgbox.com/0d/69/xhW1KYRz_o.jpg",
          "https://images2.imgbox.com/b1/ff/dXPM5ami_o.png"
        ]
      }
    },
    "37.1": {
      "title": "Capítulo 37.1 - Anúncio Segunda Temporada",
      "groups": {
        "Valkyriescan": [
          "https://images2.imgbox.com/e0/11/02zCYsOY_o.jpg",
          "https://images2.imgbox.com/85/7c/tXfbNr1G_o.png"
        ]
      }
    },
    "37": {
      "title": "Capítulo 37 - Conclusão",
      "groups": {
        "Valkyriescan": [
          "https://images2.imgbox.com/99/c5/E9mgeVJU_o.jpg",
          "https://images2.imgbox.com/a0/5e/6aM4tCz1_o.png",
          "https://images2.imgbox.com/d7/11/QQn05yI8_o.png",
          "https://images2.imgbox.com/da/2a/Omo7VyRo_o.png",
          "https://images2.imgbox.com/7c/a0/NLcVzLZg_o.png",
          "https://images2.imgbox.com/34/9e/XEjiXZkQ_o.png",
          "https://images2.imgbox.com/92/6f/X77JS7FM_o.png"
        ]
      }
    },
    "36": {
      "title": "Capítulo 36 - Está vendo coisa onde não tem",
      "groups": {
        "Valkyriescan": [
          "https://images2.imgbox.com/d8/85/mVMq3cwU_o.jpg",
          "https://images2.imgbox.com/03/f2/q8vRhWjD_o.png",
          "https://images2.imgbox.com/af/b7/Au42Mho5_o.png",
          "https://images2.imgbox.com/a1/39/TZ5SF57H_o.png",
          "https://images2.imgbox.com/ec/bd/WvJpDKje_o.png",
          "https://images2.imgbox.com/3c/9d/yKpOduiI_o.png",
          "https://images2.imgbox.com/e3/fd/xzIfTVpi_o.png",
          "https://images2.imgbox.com/e2/4b/JN8o58oQ_o.png"
        ]
      }
    },
    "35": {
      "title": "Capítulo 35 - Quero ver",
      "groups": {
        "Valkyriescan": [
          "https://images2.imgbox.com/40/13/pdQuCkhr_o.jpg",
          "https://images2.imgbox.com/bb/4e/8oPstWtI_o.png",
          "https://images2.imgbox.com/5a/3f/KjN0tuxT_o.png",
          "https://images2.imgbox.com/64/56/oTTUjWoa_o.png",
          "https://images2.imgbox.com/be/f1/eg40rzir_o.png",
          "https://images2.imgbox.com/3f/3e/SH0cc9lI_o.png",
          "https://images2.imgbox.com/34/2c/5jKUWgnk_o.png"
        ]
      }
    },
    "34": {
      "title": "Capítulo 34 - A última prova do ensino médio",
      "groups": {
        "Valkyriescan": [
          "https://images2.imgbox.com/25/97/8k5mkZiL_o.jpg",
          "https://images2.imgbox.com/65/47/ExM5atEn_o.jpg",
          "https://images2.imgbox.com/3f/0f/EdGSMvmn_o.jpg",
          "https://images2.imgbox.com/92/ca/mMGciifO_o.jpg",
          "https://images2.imgbox.com/0b/68/hL7lAQd3_o.jpg",
          "https://images2.imgbox.com/10/8b/1J8gDufW_o.jpg",
          "https://images2.imgbox.com/26/cd/IOGHiYq9_o.jpg",
          "https://images2.imgbox.com/4c/47/jS4xQw23_o.jpg"
        ]
      }
    },
    "33": {
      "title": "Capítulo 33 - Os métodos da mãe da Tong",
      "groups": {
        "Valkyriescan": [
          "https://images2.imgbox.com/54/37/h7SRUlly_o.jpg",
          "https://images2.imgbox.com/3e/a1/FU2JTmk7_o.jpg",
          "https://images2.imgbox.com/58/cf/H3Escsgv_o.jpg",
          "https://images2.imgbox.com/36/85/x40LB5W5_o.jpg",
          "https://images2.imgbox.com/ee/4e/78xJ3hI2_o.jpg",
          "https://images2.imgbox.com/4d/85/pgwkVhl2_o.jpg",
          "https://images2.imgbox.com/9b/ba/fiUZ0yRT_o.jpg",
          "https://images2.imgbox.com/02/26/IYlV4Hpu_o.jpg"
        ]
      }
    },
    "32": {
      "title": "Capítulo 32 - Ligando para a mamãe",
      "groups": {
        "Valkyriescan": [
          "https://images2.imgbox.com/ad/f3/ElMhurhF_o.jpg",
          "https://images2.imgbox.com/db/5b/tM6sFXPl_o.jpg",
          "https://images2.imgbox.com/3f/ce/MNJiXYRC_o.jpg",
          "https://images2.imgbox.com/70/ce/Lm7krY1a_o.jpg",
          "https://images2.imgbox.com/04/d3/5vSIZvIK_o.jpg",
          "https://images2.imgbox.com/eb/92/79hSmHAX_o.jpg",
          "https://images2.imgbox.com/e9/4e/rJI1bYVG_o.jpg"
        ]
      }
    },
    "31": {
      "title": "Capítulo 31 - Xiao Lu chorou",
      "groups": {
        "Valkyriescan": [
          "https://images2.imgbox.com/49/b9/OGzj4tqD_o.jpg",
          "https://images2.imgbox.com/5c/e3/BStlf18Y_o.jpg",
          "https://images2.imgbox.com/97/46/8z1Aox2A_o.jpg",
          "https://images2.imgbox.com/9e/46/G1PSVphb_o.jpg",
          "https://images2.imgbox.com/56/91/BNl5jS5m_o.jpg",
          "https://images2.imgbox.com/72/6d/1XK3F3KN_o.jpg",
          "https://images2.imgbox.com/95/3c/8TZbEMXs_o.jpg",
          "https://images2.imgbox.com/99/f9/Abgvvpkm_o.jpg"
        ]
      }
    },
    "30": {
      "title": "Capítulo 30 - Expostas",
      "groups": {
        "Valkyriescan": [
          "https://images2.imgbox.com/ae/d5/kPXl8vDI_o.jpg",
          "https://images2.imgbox.com/55/4f/89WiaTiC_o.jpg",
          "https://images2.imgbox.com/36/6e/S88ayVo7_o.jpg",
          "https://images2.imgbox.com/cc/17/ZB7pjnJN_o.jpg",
          "https://images2.imgbox.com/7e/ae/NWU9tGSo_o.jpg",
          "https://images2.imgbox.com/56/a5/ljFY1rzh_o.jpg",
          "https://images2.imgbox.com/a4/e5/Xnj6HVnT_o.jpg"
        ]
      }
    },
    "29": {
      "title": "Capítulo 29 - Você não entende",
      "groups": {
        "Valkyriescan": [
          "https://images2.imgbox.com/f7/cd/AjIqRFUn_o.jpg",
          "https://images2.imgbox.com/58/87/7uU0Zcca_o.jpg",
          "https://images2.imgbox.com/36/db/IbFeSKYE_o.jpg",
          "https://images2.imgbox.com/a7/31/CGqEV9kC_o.jpg",
          "https://images2.imgbox.com/26/73/YyqbOOzy_o.jpg",
          "https://images2.imgbox.com/26/f7/J91uxWDZ_o.jpg",
          "https://images2.imgbox.com/47/45/AyDSgCcs_o.jpg"
        ]
      }
    },
    "28": {
      "title": "Capítulo 28 - O que aconteceu?",
      "groups": {
        "Valkyriescan": [
          "https://images2.imgbox.com/f5/4c/DoTUIKSc_o.jpg",
          "https://images2.imgbox.com/dd/e4/66GTI7sG_o.jpg",
          "https://images2.imgbox.com/88/47/64mqJaki_o.jpg",
          "https://images2.imgbox.com/bb/ea/2qjOAp8v_o.jpg",
          "https://images2.imgbox.com/f1/ec/nhf3BlPC_o.jpg",
          "https://images2.imgbox.com/67/d1/oGEgE20S_o.jpg",
          "https://images2.imgbox.com/db/48/roTt80eS_o.jpg"
        ]
      }
    },
    "27": {
      "title": "Capítulo 27 - Quer saber?",
      "groups": {
        "Valkyriescan": [
          "https://images2.imgbox.com/ab/44/9DVtjlft_o.jpg",
          "https://images2.imgbox.com/61/95/6oegNMfi_o.jpg",
          "https://images2.imgbox.com/5a/9a/vnMccEj6_o.jpg",
          "https://images2.imgbox.com/28/0c/9QjrnVwD_o.jpg",
          "https://images2.imgbox.com/cb/69/3StiIalx_o.jpg",
          "https://images2.imgbox.com/22/71/lsdGVu8I_o.jpg",
          "https://images2.imgbox.com/4f/66/IJMR9bjg_o.jpg"
        ]
      }
    },
    "26": {
      "title": "Capítulo 26 - A última razão",
      "groups": {
        "Valkyriescan": [
          "https://images2.imgbox.com/ee/02/ISAx6x19_o.jpg",
          "https://images2.imgbox.com/95/d6/QYxZMPnN_o.jpg",
          "https://images2.imgbox.com/7a/ed/NtMFWX9b_o.jpg",
          "https://images2.imgbox.com/7e/c5/Q9n43rQC_o.jpg",
          "https://images2.imgbox.com/c4/a8/5cx95ozM_o.jpg",
          "https://images2.imgbox.com/45/cd/jC43Dsa3_o.jpg",
          "https://images2.imgbox.com/74/87/4WUqve02_o.jpg"
        ]
      }
    },
    "25": {
      "title": "Capítulo 25 - Vai sim",
      "groups": {
        "Valkyriescan": [
          "https://images2.imgbox.com/ed/72/l8kX1f65_o.jpg",
          "https://images2.imgbox.com/60/74/q0KiLLrs_o.jpg",
          "https://images2.imgbox.com/bb/24/x5hpnxOB_o.jpg",
          "https://images2.imgbox.com/2d/20/jnWjqC0Z_o.jpg",
          "https://images2.imgbox.com/74/af/BTTjtV3C_o.jpg",
          "https://images2.imgbox.com/2c/f3/whfqFYzJ_o.jpg",
          "https://images2.imgbox.com/02/b2/2lLTiarD_o.jpg"
        ]
      }
    },
    "24": {
      "title": "Capítulo 24 - Não acredito",
      "groups": {
        "Valkyriescan": [
          "https://images2.imgbox.com/d3/7c/1zTqhQ2i_o.jpg",
          "https://images2.imgbox.com/84/96/Lv9g5Uzk_o.jpg",
          "https://images2.imgbox.com/c7/c9/ZX9H804M_o.jpg",
          "https://images2.imgbox.com/19/1c/TjZqFT0z_o.jpg",
          "https://images2.imgbox.com/3b/c3/P0YlInkE_o.jpg",
          "https://images2.imgbox.com/02/1c/3Ej6Bg7K_o.jpg",
          "https://images2.imgbox.com/82/3e/9Npw8DHh_o.jpg"
        ]
      }
    },
    "23": {
      "title": "Capítulo 23 - Tá namorando?",
      "groups": {
        "Valkyriescan": [
          "https://images2.imgbox.com/60/5b/IHOcLUa7_o.jpg",
          "https://images2.imgbox.com/72/ab/bTNI4VtZ_o.jpg",
          "https://images2.imgbox.com/5f/48/OnXd9WJ5_o.jpg",
          "https://images2.imgbox.com/29/19/3uEKdc7O_o.jpg",
          "https://images2.imgbox.com/37/1c/8tAM1a7J_o.jpg",
          "https://images2.imgbox.com/db/7d/SYyYBo4W_o.jpg",
          "https://images2.imgbox.com/70/e5/uz01lm2D_o.jpg",
          "https://images2.imgbox.com/13/e9/cSkMaROb_o.jpg"
        ]
      }
    },
    "22": {
      "title": "Capítulo 22 - Um beijo não foi o suficiente",
      "groups": {
        "Valkyriescan": [
          "https://images2.imgbox.com/b2/14/uKJxSeDL_o.jpg",
          "https://images2.imgbox.com/32/77/GQRTC6AK_o.jpg",
          "https://images2.imgbox.com/f5/9f/lPDU5kzM_o.jpg",
          "https://images2.imgbox.com/7f/fd/jipTy5yj_o.jpg",
          "https://images2.imgbox.com/6a/e7/LERfFLmy_o.jpg",
          "https://images2.imgbox.com/38/50/mSEeAG7J_o.jpg",
          "https://images2.imgbox.com/4a/c4/XyWSkU9D_o.jpg",
          "https://images2.imgbox.com/9b/5b/gH0JGPlH_o.jpg",
          "https://images2.imgbox.com/3c/9a/9s3nRlkd_o.jpg"
        ]
      }
    },
    "21": {
      "title": "Capítulo 21 - Beijo roubado",
      "groups": {
        "Valkyriescan": [
          "https://images2.imgbox.com/f0/8d/wm82NsbV_o.jpg",
          "https://images2.imgbox.com/8a/08/XFJoKhtJ_o.jpg",
          "https://images2.imgbox.com/3d/c5/gWyfcRsi_o.jpg",
          "https://images2.imgbox.com/01/28/9k9GyPnK_o.jpg",
          "https://images2.imgbox.com/bd/13/zJwaPDUe_o.jpg",
          "https://images2.imgbox.com/8f/8b/ZynakDFB_o.jpg",
          "https://images2.imgbox.com/6e/e4/s9YRk5UU_o.jpg",
          "https://images2.imgbox.com/24/54/AW9qzXMe_o.jpg"
        ]
      }
    },
    "20": {
      "title": "Capítulo 20 - Conversas noturnas no grupo",
      "groups": {
        "Valkyriescan": [
          "https://images2.imgbox.com/39/7e/6lh6W9a1_o.jpg",
          "https://images2.imgbox.com/9c/dd/CASMI0i0_o.jpg",
          "https://images2.imgbox.com/16/5b/E4oSTTBK_o.jpg",
          "https://images2.imgbox.com/38/57/gjrqHabT_o.jpg",
          "https://images2.imgbox.com/61/79/Gk9HdJdv_o.jpg",
          "https://images2.imgbox.com/c2/b8/1fqa8Q5g_o.jpg",
          "https://images2.imgbox.com/09/fa/RTDFa7mB_o.jpg",
          "https://images2.imgbox.com/55/a4/izpbxS3U_o.jpg",
          "https://images2.imgbox.com/39/e9/800cGgwW_o.jpg",
          "https://images2.imgbox.com/6f/85/naSGcQ3u_o.jpg"
        ]
      }
    },
    "19": {
      "title": "Capítulo 19 - Isso é bom",
      "groups": {
        "Valkyriescan": [
          "https://images2.imgbox.com/a9/41/p0X6dDnw_o.jpg",
          "https://images2.imgbox.com/48/61/Fm5fG0HQ_o.jpg",
          "https://images2.imgbox.com/f4/c2/OL2niQuC_o.jpg",
          "https://images2.imgbox.com/ff/8a/CNO0jgEm_o.jpg",
          "https://images2.imgbox.com/75/14/6Ruj5Qgw_o.jpg",
          "https://images2.imgbox.com/7d/bb/LtX2J4CM_o.jpg",
          "https://images2.imgbox.com/22/01/vQRYW4sw_o.jpg"
        ]
      }
    },
    "18": {
      "title": "Capítulo 18 - Você é Tong Tong?",
      "groups": {
        "Valkyriescan": [
          "https://images2.imgbox.com/6f/4f/DCyFgxdF_o.jpg",
          "https://images2.imgbox.com/9a/3c/jIoluEKV_o.jpg",
          "https://images2.imgbox.com/b5/f0/tPwwrfKf_o.jpg",
          "https://images2.imgbox.com/1c/b9/RfVyI1SI_o.jpg",
          "https://images2.imgbox.com/e7/8d/yyihTbXl_o.jpg",
          "https://images2.imgbox.com/0f/62/EUd3goly_o.jpg",
          "https://images2.imgbox.com/11/d3/h4PohZ5m_o.jpg"
        ]
      }
    },
    "17": {
      "title": "Capítulo 17 - Quero namorar",
      "groups": {
        "Valkyriescan": [
          "https://images2.imgbox.com/73/2b/99kBDfzj_o.jpg",
          "https://images2.imgbox.com/43/02/2BcjUko3_o.jpg",
          "https://images2.imgbox.com/53/c1/lofP6aaM_o.jpg",
          "https://images2.imgbox.com/e0/f6/CDYWrPfD_o.jpg",
          "https://images2.imgbox.com/14/1e/hZ1OMUhi_o.jpg",
          "https://images2.imgbox.com/f3/cb/0Vhdv584_o.jpg",
          "https://images2.imgbox.com/d4/7b/KQOSGiLV_o.jpg"
        ]
      }
    },
    "16": {
      "title": "Capítulo 16 - Realmente gosto",
      "groups": {
        "Valkyriescan": [
          "https://images2.imgbox.com/b9/6f/YPSoWY2a_o.jpg",
          "https://images2.imgbox.com/c1/97/uPVV3m2X_o.jpg",
          "https://images2.imgbox.com/7e/81/XeCKWgQN_o.jpg",
          "https://images2.imgbox.com/8a/6c/MG5FNtU3_o.jpg",
          "https://images2.imgbox.com/82/62/2T0nXggs_o.jpg",
          "https://images2.imgbox.com/63/27/vbs0x1sA_o.jpg",
          "https://images2.imgbox.com/6e/8d/lq7BygAf_o.jpg",
          "https://images2.imgbox.com/8c/c7/0oneiQPB_o.jpg"
        ]
      }
    },
    "15": {
      "title": "Capítulo 15 - É amor?",
      "groups": {
        "Valkyriescan": [
          "https://images2.imgbox.com/68/5b/6B1VnANC_o.jpg",
          "https://images2.imgbox.com/c2/ef/aJmgbFzl_o.jpg",
          "https://images2.imgbox.com/06/5a/HB1hUe8b_o.jpg",
          "https://images2.imgbox.com/30/99/DKaexZvp_o.jpg",
          "https://images2.imgbox.com/e8/72/3KZXoD3l_o.jpg",
          "https://images2.imgbox.com/3e/48/2qTO8RV4_o.jpg",
          "https://images2.imgbox.com/bd/12/lOmTwldI_o.jpg"
        ]
      }
    },
    "14": {
      "title": "Capítulo 14 - Amigas... Não fariam isso, né?",
      "groups": {
        "Valkyriescan": [
          "https://images2.imgbox.com/14/6b/J79PhHiY_o.jpg",
          "https://images2.imgbox.com/71/a2/XI4NG69r_o.jpg",
          "https://images2.imgbox.com/55/27/s8lOT3jI_o.jpg",
          "https://images2.imgbox.com/d0/bf/aohI0E5C_o.jpg",
          "https://images2.imgbox.com/0d/d1/HbJqMWFX_o.jpg",
          "https://images2.imgbox.com/2c/84/1DJmd9We_o.jpg",
          "https://images2.imgbox.com/c7/b0/g2VepLpA_o.jpg",
          "https://images2.imgbox.com/cb/ad/xBdAaBRp_o.jpg"
        ]
      }
    },
    "13": {
      "title": "Capítulo 13 - Ciúmes",
      "groups": {
        "Valkyriescan": [
          "https://images2.imgbox.com/16/8f/OvnQqx4a_o.jpg",
          "https://images2.imgbox.com/1f/25/mdqIGaDe_o.jpg",
          "https://images2.imgbox.com/d2/3a/FdeUnQPg_o.jpg",
          "https://images2.imgbox.com/dc/a2/BwOlGxMN_o.jpg",
          "https://images2.imgbox.com/51/a8/gvIzkS8n_o.jpg",
          "https://images2.imgbox.com/c2/fd/HGrR61pZ_o.jpg",
          "https://images2.imgbox.com/6e/1e/SUXA7wrQ_o.jpg",
          "https://images2.imgbox.com/57/f9/wtstC3eV_o.jpg"
        ]
      }
    },
    "12": {
      "title": "Capítulo 12 - Quero Saber",
      "groups": {
        "Valkyriescan": [
          "https://images2.imgbox.com/b1/cc/OokmZh2W_o.jpg",
          "https://images2.imgbox.com/f5/c3/7DaVFVY6_o.jpg",
          "https://images2.imgbox.com/20/cd/tjQB9sJz_o.jpg",
          "https://images2.imgbox.com/83/8f/mWA1f8Xn_o.jpg",
          "https://images2.imgbox.com/4c/4e/hUh0hDum_o.jpg",
          "https://images2.imgbox.com/f3/93/p8Woe43w_o.jpg",
          "https://images2.imgbox.com/32/08/bTA7SzXx_o.jpg",
          "https://images2.imgbox.com/74/ca/BQYItKwy_o.jpg",
          "https://images2.imgbox.com/17/58/dqlMVAc8_o.jpg"
        ]
      }
    },
    "11": {
      "title": "Capítulo 11 - Eu fico muito feliz",
      "groups": {
        "Valkyriescan": [
          "https://images2.imgbox.com/e9/20/C9RnI2ie_o.jpg",
          "https://images2.imgbox.com/a5/2f/DKs04Rcp_o.jpg",
          "https://images2.imgbox.com/bc/96/nsyL83bx_o.jpg",
          "https://images2.imgbox.com/07/22/TKVSGwQW_o.jpg",
          "https://images2.imgbox.com/5d/49/XALoADmz_o.jpg",
          "https://images2.imgbox.com/4a/73/UepwhyUW_o.jpg",
          "https://images2.imgbox.com/78/4d/g4BPczRg_o.jpg",
          "https://images2.imgbox.com/df/30/VS4tyj8J_o.jpg"
        ]
      }
    },
    "10": {
      "title": "Capítulo 10 - Diferente",
      "groups": {
        "Valkyriescan": [
          "https://images2.imgbox.com/5e/22/oXGo3n5c_o.jpg",
          "https://images2.imgbox.com/04/6a/ELolXHbO_o.jpg",
          "https://images2.imgbox.com/60/db/3PGiI83M_o.jpg",
          "https://images2.imgbox.com/c4/69/9Gj3WTG6_o.jpg",
          "https://images2.imgbox.com/8c/7c/AHSiU3Jb_o.jpg",
          "https://images2.imgbox.com/d0/ee/rduk781W_o.jpg",
          "https://images2.imgbox.com/83/ee/iRj7tMnT_o.jpg",
          "https://images2.imgbox.com/db/88/P7EoSBx5_o.jpg",
          "https://images2.imgbox.com/a8/c1/Obc8s1XI_o.jpg",
          "https://images2.imgbox.com/a2/f9/JHcRa72K_o.jpg"
        ]
      }
    },
    "9": {
      "title": "Capítulo 9 - Chorando...?",
      "groups": {
        "Valkyriescan": [
          "https://images2.imgbox.com/43/57/mc1s5smk_o.jpg",
          "https://images2.imgbox.com/b3/23/ZLUgno3c_o.jpg",
          "https://images2.imgbox.com/64/7d/Uf9ooTXB_o.jpg",
          "https://images2.imgbox.com/74/ea/JdDDOn9i_o.jpg",
          "https://images2.imgbox.com/d1/7c/j9NQRrKh_o.jpg",
          "https://images2.imgbox.com/bd/02/3hOTP7Wv_o.jpg",
          "https://images2.imgbox.com/61/a6/LXzbxTsk_o.jpg",
          "https://images2.imgbox.com/5d/17/r0OgiFYF_o.jpg"
        ]
      }
    },
    "8": {
      "title": "Capítulo 8 - Mulheres são todas falsas",
      "groups": {
        "Valkyriescan": [
          "https://images2.imgbox.com/86/cd/N4GuSR4L_o.jpg",
          "https://images2.imgbox.com/6a/ea/ukggM8vh_o.jpg",
          "https://images2.imgbox.com/68/4d/5TRUisSz_o.jpg",
          "https://images2.imgbox.com/11/5d/w7YMDiao_o.jpg",
          "https://images2.imgbox.com/35/97/xlhBJkk8_o.jpg",
          "https://images2.imgbox.com/b1/04/cpilueGK_o.jpg",
          "https://images2.imgbox.com/6c/11/R6NYAAWn_o.jpg",
          "https://images2.imgbox.com/0e/ca/ndwf6AeS_o.jpg"
        ]
      }
    },
    "7": {
      "title": "Capítulo 7 - Vamos fazer aquilo...",
      "groups": {
        "Valkyriescan": [
          "https://images2.imgbox.com/5e/3d/zWt1Rp4R_o.jpg",
          "https://images2.imgbox.com/76/02/troea5ZS_o.jpg",
          "https://images2.imgbox.com/1f/96/QPqNWoxC_o.jpg",
          "https://images2.imgbox.com/4b/52/PZM00osI_o.jpg",
          "https://images2.imgbox.com/f2/8a/GpDlocdV_o.jpg",
          "https://images2.imgbox.com/12/b5/t4criAMU_o.jpg",
          "https://images2.imgbox.com/77/78/rH008W6M_o.jpg",
          "https://images2.imgbox.com/c0/01/gCBdDhHS_o.jpg"
        ]
      }
    },
    "6.6": {
      "title": "Capítulo 6.6 - Especial Ano Novo Lunar",
      "groups": {
        "Valkyriescan": [
          "https://images2.imgbox.com/1a/25/Yr72oMIR_o.jpg",
          "https://images2.imgbox.com/28/50/lRiIjmSq_o.jpg",
          "https://images2.imgbox.com/c3/21/hMyOHHyo_o.jpg",
          "https://images2.imgbox.com/3c/eb/50Urvsyf_o.jpg",
          "https://images2.imgbox.com/5b/b4/rOvwwF7F_o.jpg"
        ]
      }
    },
    "6.5": {
      "title": "Capítulo 6.5 - Especial Dia dos Namorados",
      "groups": {
        "Valkyriescan": [
          "https://images2.imgbox.com/4f/fa/Q1u8B7ld_o.jpg",
          "https://images2.imgbox.com/d2/ce/1IK6X8y3_o.jpg",
          "https://images2.imgbox.com/73/77/5xB63z0T_o.jpg",
          "https://images2.imgbox.com/4d/45/MvqTSSro_o.jpg",
          "https://images2.imgbox.com/f4/6e/JWczBjhC_o.jpg"
        ]
      }
    },
    "6": {
      "title": "Capítulo 6 - Preocupação inexplicável?",
      "groups": {
        "Valkyriescan": [
          "https://images2.imgbox.com/74/29/QwofMg9f_o.jpg",
          "https://images2.imgbox.com/8e/d2/xtjfEhcM_o.jpg",
          "https://images2.imgbox.com/8e/f5/awssaofV_o.jpg",
          "https://images2.imgbox.com/6f/77/lO9ElXGM_o.jpg",
          "https://images2.imgbox.com/a8/0e/svbVzs9Q_o.jpg",
          "https://images2.imgbox.com/2d/65/fdxvww3f_o.jpg",
          "https://images2.imgbox.com/ff/d3/vuJeYkGz_o.jpg",
          "https://images2.imgbox.com/10/ee/sKik6RgB_o.jpg",
          "https://images2.imgbox.com/d8/4d/WaGERIdV_o.jpg",
          "https://images2.imgbox.com/4d/47/ZthKjc4W_o.jpg"
        ]
      }
    },
    "5": {
      "title": "Capítulo 5 - Não é necessariamente uma criança ruim, né?",
      "groups": {
        "Valkyriescan": [
          "https://images2.imgbox.com/fe/e8/KqmPmpaS_o.jpg",
          "https://images2.imgbox.com/e8/e2/4EgYBA65_o.jpg",
          "https://images2.imgbox.com/bd/6c/H6kp0370_o.jpg",
          "https://images2.imgbox.com/fa/69/cms3kv5U_o.jpg",
          "https://images2.imgbox.com/a1/35/BIQFUS0r_o.jpg",
          "https://images2.imgbox.com/fd/98/9BqKbOh5_o.jpg",
          "https://images2.imgbox.com/92/23/6NQBt5VG_o.jpg",
          "https://images2.imgbox.com/8d/d3/fcv386XE_o.jpg",
          "https://images2.imgbox.com/6c/53/77kx14Ot_o.jpg"
        ]
      }
    },
    "4": {
      "title": "Capítulo 4 - A mãe da filhinha de mamãe",
      "groups": {
        "Valkyriescan": [
          "https://images2.imgbox.com/1b/1f/4cbpXx8x_o.jpg",
          "https://images2.imgbox.com/44/7b/iUiesq61_o.jpg",
          "https://images2.imgbox.com/9e/de/h8qRhVWy_o.jpg",
          "https://images2.imgbox.com/f7/38/d1OI0PaY_o.jpg",
          "https://images2.imgbox.com/49/f5/9KI1Ldfg_o.jpg",
          "https://images2.imgbox.com/1d/54/fwvbVEri_o.jpg",
          "https://images2.imgbox.com/fa/fd/abA0vY1N_o.jpg",
          "https://images2.imgbox.com/7b/9e/lMEMlVFu_o.jpg",
          "https://images2.imgbox.com/9a/cb/2JDWkOsm_o.jpg",
          "https://images2.imgbox.com/37/e8/77KXMc41_o.jpg",
          "https://images2.imgbox.com/6c/56/a6mX0NZ9_o.jpg"
        ]
      }
    },
    "3": {
      "title": "Capítulo 3 - Chorona? Filhinha de mamãe?",
      "groups": {
        "Valkyriescan": [
          "https://images2.imgbox.com/df/8b/nSfiFJWK_o.jpg",
          "https://images2.imgbox.com/b0/76/uU4rfE7a_o.jpg",
          "https://images2.imgbox.com/c9/e2/MJA8JKC5_o.jpg",
          "https://images2.imgbox.com/1b/06/I5aWVKpL_o.jpg",
          "https://images2.imgbox.com/cd/cc/h9RjP7tb_o.jpg",
          "https://images2.imgbox.com/30/5b/BC0rY8JP_o.jpg",
          "https://images2.imgbox.com/bf/45/vGJiX0ft_o.jpg",
          "https://images2.imgbox.com/c6/ee/9UBKQCjO_o.jpg"
        ]
      }
    },
    "2": {
      "title": "Capítulo 2 - Acordo?",
      "groups": {
        "Valkyriescan": [
          "https://images2.imgbox.com/e9/d0/wOeqNWmj_o.jpg",
          "https://images2.imgbox.com/cb/c9/qGcbSDPH_o.jpg",
          "https://images2.imgbox.com/6f/ed/3n9FS9Lf_o.jpg",
          "https://images2.imgbox.com/49/13/ozjszx1L_o.jpg",
          "https://images2.imgbox.com/0a/31/xRZvkR3h_o.jpg",
          "https://images2.imgbox.com/94/71/aAKArIvW_o.jpg",
          "https://images2.imgbox.com/72/ac/NP5fQYTW_o.jpg",
          "https://images2.imgbox.com/1c/e1/9dup6GaP_o.jpg"
        ]
      }
    },
    "1": {
      "title": "Capítulo 1 - Fui ameaçada por ela?",
      "groups": {
        "Valkyriescan": [
          "https://images2.imgbox.com/fe/3a/mjDhNBmY_o.png",
          "https://images2.imgbox.com/6e/a5/Y2t4DfAK_o.jpg",
          "https://images2.imgbox.com/bf/56/2jR4ZAT6_o.jpg",
          "https://images2.imgbox.com/9e/39/FyVcbJae_o.jpg",
          "https://images2.imgbox.com/6e/a4/OnXvj8C0_o.jpg",
          "https://images2.imgbox.com/e5/ca/tt53Jecp_o.jpg",
          "https://images2.imgbox.com/3e/67/kAsTngtz_o.png"
        ]
      }
    },
    "0": {
      "title": "Capítulo 0 - Prévia",
      "groups": {
        "Valkyriescan": [
          "https://images2.imgbox.com/9b/ec/UOPu2qV7_o.png",
          "https://images2.imgbox.com/91/cf/VDo9EC3f_o.jpg",
          "https://images2.imgbox.com/e4/7c/ZJcY3EDQ_o.jpg",
          "https://images2.imgbox.com/f7/24/uOwDeNS1_o.jpg",
          "https://images2.imgbox.com/39/7c/ZRF9XOb9_o.jpg",
          "https://images2.imgbox.com/2c/92/3qVNSj6K_o.png"
        ]
      }
    }
  }
}