{
  "title": "Yuri Is My Job!",
  "author": "Miman",
  "artist": "Miman",
  "description": "Hime é uma garota que desenvolveu sua fofura de forma intencional com o plano de se casar com um bilionário. Um dia, ela é mais ou menos forçada a trabalhar como substituta de uma garota ferida por esbarrar com ela na rua. O local de trabalho é um café temático onde as garçonetes fazem um show como se o café fosse administrado pela escola ojousama de yuri clichê. Há um grande contraste entre as apresentações e a equipe fora de serviço.",
  "cover": "https://images2.imgbox.com/99/70/9NbR7C7i_o.jpg",
  "status": "Em lançamento",
  "chapters": {
    "16": {
      "title": "Capítulo 16",
      "groups": {
        "Valkyriescan": [
          "https://images2.imgbox.com/a8/9e/CLdPFTEE_o.png",
          "https://images2.imgbox.com/1e/43/qhHQw2zu_o.jpg",
          "https://images2.imgbox.com/e6/db/eCaCc8iI_o.jpg",
          "https://images2.imgbox.com/df/3c/BQhAfzAC_o.jpg",
          "https://images2.imgbox.com/37/24/lBDMA1Ax_o.jpg",
          "https://images2.imgbox.com/7a/a5/kA66BvFA_o.jpg",
          "https://images2.imgbox.com/e8/e2/byCJnIr4_o.jpg",
          "https://images2.imgbox.com/42/61/ywMnUAsx_o.jpg",
          "https://images2.imgbox.com/13/4f/wMY1xS6T_o.jpg",
          "https://images2.imgbox.com/38/49/4hy9j6Yt_o.jpg",
          "https://images2.imgbox.com/fd/be/c9x4ijWh_o.jpg",
          "https://images2.imgbox.com/b9/08/8ZNHMhvJ_o.jpg",
          "https://images2.imgbox.com/13/3a/LqDMqnfx_o.jpg",
          "https://images2.imgbox.com/44/a6/dfrIGZ6n_o.jpg",
          "https://images2.imgbox.com/8a/92/oBPFRlAc_o.jpg",
          "https://images2.imgbox.com/d9/d3/4Yh8QQAl_o.jpg",
          "https://images2.imgbox.com/9f/9f/2HAOTDgt_o.jpg",
          "https://images2.imgbox.com/5f/04/Xl8Amzjx_o.jpg",
          "https://images2.imgbox.com/c0/d2/sJ3xHuBI_o.jpg",
          "https://images2.imgbox.com/8d/ef/6Bp2Q32F_o.jpg",
          "https://images2.imgbox.com/52/f6/JIIG8e7e_o.jpg",
          "https://images2.imgbox.com/48/50/5qbZeQyP_o.jpg",
          "https://images2.imgbox.com/f6/b9/SWElAkla_o.jpg",
          "https://images2.imgbox.com/61/29/UXQV7CsT_o.jpg",
          "https://images2.imgbox.com/64/82/S8PRtvfv_o.jpg",
          "https://images2.imgbox.com/0e/f0/9thuKMLR_o.jpg",
          "https://images2.imgbox.com/f4/b0/jQ6qEtGw_o.jpg",
          "https://images2.imgbox.com/37/a5/RxEQgZnq_o.jpg",
          "https://images2.imgbox.com/16/55/4eB48XSI_o.jpg",
          "https://images2.imgbox.com/b9/9b/4rqREf1F_o.jpg",
          "https://images2.imgbox.com/25/84/kzvb5T82_o.jpg",
          "https://images2.imgbox.com/8d/99/ZyFal2BQ_o.jpg",
          "https://images2.imgbox.com/b9/99/SOGxv2qb_o.jpg",
          "https://images2.imgbox.com/ce/f9/3uG4qamf_o.jpg",
          "https://images2.imgbox.com/e1/f1/Nby1wWym_o.jpg",
          "https://images2.imgbox.com/cc/4d/Wc3AT4f3_o.jpg",
          "https://images2.imgbox.com/d3/7f/xShRwIBK_o.jpg",
          "https://images2.imgbox.com/2d/c2/R7DUtkel_o.jpg",
          "https://images2.imgbox.com/45/9f/kcBtojZ3_o.jpg",
          "https://images2.imgbox.com/10/c4/1HmqIdDA_o.jpg",
          "https://images2.imgbox.com/b1/c5/u9tVQW4v_o.jpg",
          "https://images2.imgbox.com/71/98/RMME4pdB_o.jpg"
        ]
      }
    },
    "15": {
      "title": "Capítulo 15",
      "groups": {
        "Valkyriescan": [
          "https://images2.imgbox.com/57/2f/wAOdhk8r_o.png",
          "https://images2.imgbox.com/62/c3/gmF1MJxb_o.jpg",
          "https://images2.imgbox.com/ae/72/c8uh5uTH_o.jpg",
          "https://images2.imgbox.com/a2/33/xe8JziUS_o.jpg",
          "https://images2.imgbox.com/5a/f6/yShCGUlX_o.jpg",
          "https://images2.imgbox.com/39/78/4wUfRJS4_o.jpg",
          "https://images2.imgbox.com/b5/5e/G2H8h8Iy_o.jpg",
          "https://images2.imgbox.com/bb/fb/MWnYAaJu_o.jpg",
          "https://images2.imgbox.com/3c/d7/DYfkN7E4_o.jpg",
          "https://images2.imgbox.com/07/3b/RxPK6DNa_o.jpg",
          "https://images2.imgbox.com/b4/a6/CEZ6syG3_o.jpg",
          "https://images2.imgbox.com/9c/8f/hparTLyT_o.jpg",
          "https://images2.imgbox.com/9d/11/iY6ze6XJ_o.jpg",
          "https://images2.imgbox.com/9d/9d/dobKJOxd_o.jpg",
          "https://images2.imgbox.com/06/86/6W7a3388_o.jpg",
          "https://images2.imgbox.com/43/fe/MR92tthN_o.jpg",
          "https://images2.imgbox.com/ff/b6/ikyHbtEy_o.jpg",
          "https://images2.imgbox.com/48/87/82WhlHcB_o.jpg",
          "https://images2.imgbox.com/5f/ca/QEl53clN_o.jpg",
          "https://images2.imgbox.com/e6/34/xk0APxE1_o.jpg",
          "https://images2.imgbox.com/81/2d/37CihSvj_o.jpg",
          "https://images2.imgbox.com/50/ed/oX5247Cy_o.jpg",
          "https://images2.imgbox.com/47/6a/rz9jzegA_o.jpg",
          "https://images2.imgbox.com/46/5f/RMyvX2ZT_o.jpg",
          "https://images2.imgbox.com/24/c4/BKsAHGh6_o.jpg",
          "https://images2.imgbox.com/e8/bc/f9K9kXu9_o.jpg",
          "https://images2.imgbox.com/79/8a/CUaPe7u7_o.jpg",
          "https://images2.imgbox.com/c5/3e/LuhLF7s0_o.jpg",
          "https://images2.imgbox.com/f0/02/I2VmrAkf_o.jpg"
        ]
      }
    },
    "14": {
      "title": "Capítulo 14",
      "groups": {
        "Valkyriescan": [
          "https://images2.imgbox.com/e5/1f/eU2qDj1l_o.png",
          "https://images2.imgbox.com/a4/44/Eef8mucM_o.jpg",
          "https://images2.imgbox.com/07/c0/WdZ1QCFs_o.jpg",
          "https://images2.imgbox.com/2b/91/aCRNMi04_o.jpg",
          "https://images2.imgbox.com/a2/a2/X6LzYoyH_o.jpg",
          "https://images2.imgbox.com/07/2e/d2E50fY3_o.jpg",
          "https://images2.imgbox.com/93/4b/Ro9kUjI0_o.jpg",
          "https://images2.imgbox.com/af/50/AQjmkINS_o.jpg",
          "https://images2.imgbox.com/2d/77/fngvU0cS_o.jpg",
          "https://images2.imgbox.com/56/c8/rlZHDdFy_o.jpg",
          "https://images2.imgbox.com/f1/a5/MLT1Mb6q_o.jpg",
          "https://images2.imgbox.com/d3/ab/266vNHPc_o.jpg",
          "https://images2.imgbox.com/e2/bd/9gnS99i3_o.jpg",
          "https://images2.imgbox.com/f3/38/mXaJIZne_o.jpg",
          "https://images2.imgbox.com/f1/1e/kwmQm5N2_o.jpg",
          "https://images2.imgbox.com/e6/2a/mK9p7DxP_o.jpg",
          "https://images2.imgbox.com/29/83/2kw4YXSM_o.jpg",
          "https://images2.imgbox.com/f1/02/g4XqHX3h_o.jpg",
          "https://images2.imgbox.com/68/d4/w0Se4YiG_o.jpg",
          "https://images2.imgbox.com/db/74/tTsuPSgu_o.jpg",
          "https://images2.imgbox.com/73/83/hyHsqR1u_o.jpg",
          "https://images2.imgbox.com/12/ee/wqj3qHoc_o.jpg",
          "https://images2.imgbox.com/08/f7/uXjrIARu_o.jpg",
          "https://images2.imgbox.com/a4/28/KNHwWLYm_o.jpg",
          "https://images2.imgbox.com/af/b4/XOs0D8FD_o.jpg",
          "https://images2.imgbox.com/18/cb/wMG27lEP_o.jpg",
          "https://images2.imgbox.com/6e/d0/PEfQ1FbY_o.jpg",
          "https://images2.imgbox.com/68/72/8wtSWVSh_o.jpg",
          "https://images2.imgbox.com/8a/f6/6yNyx9FE_o.jpg"
        ]
      }
    },
    "13": {
      "title": "Capítulo 13",
      "groups": {
        "Valkyriescan": [
          "https://images2.imgbox.com/86/96/kXOnU69Y_o.png",
          "https://images2.imgbox.com/75/53/nNiKsQgM_o.jpg",
          "https://images2.imgbox.com/8f/e3/IK4sLe0k_o.jpg",
          "https://images2.imgbox.com/1c/db/UyE3rWv7_o.jpg",
          "https://images2.imgbox.com/a7/2a/aNMmXAl2_o.jpg",
          "https://images2.imgbox.com/c7/fe/nCvEoj95_o.jpg",
          "https://images2.imgbox.com/28/2d/O6cf0Jqb_o.jpg",
          "https://images2.imgbox.com/16/42/aYPqaL0H_o.jpg",
          "https://images2.imgbox.com/9a/36/gT8QhuVr_o.jpg",
          "https://images2.imgbox.com/0c/57/MbZooIAe_o.jpg",
          "https://images2.imgbox.com/d2/eb/MYtpKqCj_o.jpg",
          "https://images2.imgbox.com/6f/4a/IJVt9ckL_o.jpg",
          "https://images2.imgbox.com/e7/0f/ApQ4wKD6_o.jpg",
          "https://images2.imgbox.com/b6/37/fnkyl2CM_o.jpg",
          "https://images2.imgbox.com/69/d7/YnOn6YJ4_o.jpg",
          "https://images2.imgbox.com/d7/36/hOWUPEfn_o.jpg",
          "https://images2.imgbox.com/0d/8e/J4aJSmBH_o.jpg",
          "https://images2.imgbox.com/35/b7/HNxRTYWy_o.jpg",
          "https://images2.imgbox.com/5d/f5/Etv9LyYw_o.jpg",
          "https://images2.imgbox.com/17/6b/Lg5G5AOz_o.jpg",
          "https://images2.imgbox.com/72/5c/qm3wvlYv_o.jpg",
          "https://images2.imgbox.com/1b/f1/EVfAIzPz_o.jpg",
          "https://images2.imgbox.com/20/06/0OurFWcI_o.jpg",
          "https://images2.imgbox.com/88/13/jdCRTg73_o.jpg",
          "https://images2.imgbox.com/f5/da/A3Aar205_o.jpg",
          "https://images2.imgbox.com/c5/97/RFrgBGQt_o.jpg",
          "https://images2.imgbox.com/e8/26/NJpQFOau_o.jpg",
          "https://images2.imgbox.com/e3/14/XIqgLCG9_o.jpg",
          "https://images2.imgbox.com/b6/77/7qxrJFM8_o.jpg"
        ]
      }
    },
    "12": {
      "title": "Capítulo 12",
      "groups": {
        "Valkyriescan": [
          "https://images2.imgbox.com/24/8d/OvWddGeA_o.jpg",
          "https://images2.imgbox.com/55/88/LWmCCGcu_o.jpg",
          "https://images2.imgbox.com/7a/28/S2IykuTv_o.png",
          "https://images2.imgbox.com/a4/1a/XnezCCNj_o.png",
          "https://images2.imgbox.com/01/ab/DciugIhX_o.png",
          "https://images2.imgbox.com/c7/6a/dQuxqN4h_o.png",
          "https://images2.imgbox.com/2e/5d/vXtgC3o8_o.png",
          "https://images2.imgbox.com/97/af/drRSPaoE_o.png",
          "https://images2.imgbox.com/7d/72/dswfbtJH_o.png",
          "https://images2.imgbox.com/d7/94/qIIi9bDL_o.png",
          "https://images2.imgbox.com/b0/60/4owDEtQn_o.png",
          "https://images2.imgbox.com/ac/e1/C597iElP_o.png",
          "https://images2.imgbox.com/29/03/DLiDZOvi_o.png",
          "https://images2.imgbox.com/00/12/jGzUOAZZ_o.png",
          "https://images2.imgbox.com/01/af/VZFTGtMr_o.png",
          "https://images2.imgbox.com/5e/45/klYmviaI_o.png",
          "https://images2.imgbox.com/71/9e/Ylr1snTL_o.png",
          "https://images2.imgbox.com/66/7e/gMsSv2Zl_o.png",
          "https://images2.imgbox.com/d7/eb/h1p9279x_o.png",
          "https://images2.imgbox.com/23/62/8kDsVtC5_o.png"
        ]
      }
    },
    "11.5": {
      "title": "Capítulo 11.5",
      "groups": {
        "Valkyriescan": [
          "https://images2.imgbox.com/a3/1c/GSxRTzrH_o.jpg",
          "https://images2.imgbox.com/88/fc/BICpLJO9_o.jpg",
          "https://images2.imgbox.com/6e/cd/EBeAx5CR_o.jpg",
          "https://images2.imgbox.com/64/93/SzVXeo1E_o.jpg",
          "https://images2.imgbox.com/c1/17/liutaFpG_o.jpg",
          "https://images2.imgbox.com/01/bf/vrexfRXz_o.jpg",
          "https://images2.imgbox.com/80/10/IxTzWKfo_o.jpg",
          "https://images2.imgbox.com/8f/36/kmxGsrwc_o.jpg",
          "https://images2.imgbox.com/69/bf/e9xDHu7D_o.jpg",
          "https://images2.imgbox.com/f3/61/Mk06hs39_o.jpg",
          "https://images2.imgbox.com/7d/a7/tsNmR2w2_o.png",
          "https://images2.imgbox.com/ca/9e/7gIfL9yR_o.png"
        ]
      }
    },
    "11": {
      "title": "Capítulo 11",
      "groups": {
        "Valkyriescan": [
          "https://images2.imgbox.com/55/e2/rcXL2bXd_o.jpg",
          "https://images2.imgbox.com/a8/f2/hML9RM1h_o.jpg",
          "https://images2.imgbox.com/f1/76/jP3ORdCi_o.jpg",
          "https://images2.imgbox.com/15/7c/o0X0giU4_o.jpg",
          "https://images2.imgbox.com/67/78/ZHEk3qe9_o.jpg",
          "https://images2.imgbox.com/aa/81/P3UrDM4i_o.jpg",
          "https://images2.imgbox.com/1c/6a/L4s6RJ1W_o.jpg",
          "https://images2.imgbox.com/2c/d3/m10VxqX9_o.jpg",
          "https://images2.imgbox.com/3e/a4/uvrOrNX0_o.jpg",
          "https://images2.imgbox.com/e7/66/v624nSrX_o.jpg",
          "https://images2.imgbox.com/55/64/6DIhmbVO_o.jpg",
          "https://images2.imgbox.com/57/30/wn7h6RaZ_o.jpg",
          "https://images2.imgbox.com/d5/06/Xb1WLVVd_o.jpg",
          "https://images2.imgbox.com/7b/bb/1NIIVdSs_o.jpg",
          "https://images2.imgbox.com/5f/ca/hFYx7WIl_o.jpg",
          "https://images2.imgbox.com/02/a1/zjfjK9XY_o.jpg",
          "https://images2.imgbox.com/75/c7/y9fSxf4u_o.jpg",
          "https://images2.imgbox.com/f1/c8/U972BFYF_o.jpg",
          "https://images2.imgbox.com/46/d5/YEjaXBRK_o.jpg",
          "https://images2.imgbox.com/4a/48/Pn9VbWYi_o.jpg",
          "https://images2.imgbox.com/bc/b3/rUr0tQe2_o.jpg",
          "https://images2.imgbox.com/ab/22/XblgRvBN_o.png"
        ]
      }
    },
    "10": {
      "title": "Capítulo 10",
      "groups": {
        "Valkyriescan": [
          "https://images2.imgbox.com/6f/c8/mqWVNmKI_o.jpg",
          "https://images2.imgbox.com/02/aa/zz8TYNXo_o.jpg",
          "https://images2.imgbox.com/7b/04/uAPhdilf_o.jpg",
          "https://images2.imgbox.com/22/65/09qFNus1_o.jpg",
          "https://images2.imgbox.com/ef/0d/KKMptYRo_o.jpg",
          "https://images2.imgbox.com/0f/49/xA1NAtVk_o.jpg",
          "https://images2.imgbox.com/5a/83/NL3pNGXQ_o.jpg",
          "https://images2.imgbox.com/13/6c/nIPkJJgG_o.jpg",
          "https://images2.imgbox.com/cc/19/cgreQbh7_o.jpg",
          "https://images2.imgbox.com/5c/a5/VQWVORa7_o.jpg",
          "https://images2.imgbox.com/02/c7/y8iPJQ1t_o.jpg",
          "https://images2.imgbox.com/54/e6/z7IpPPeg_o.jpg",
          "https://images2.imgbox.com/33/27/1peebVBB_o.jpg",
          "https://images2.imgbox.com/01/a2/3AVt1FpG_o.jpg",
          "https://images2.imgbox.com/a0/b5/O8OoUgbf_o.jpg",
          "https://images2.imgbox.com/af/4c/Nx5GUvVg_o.jpg",
          "https://images2.imgbox.com/23/c9/P1OHcUN5_o.jpg",
          "https://images2.imgbox.com/1d/f5/6sd2jO9e_o.jpg",
          "https://images2.imgbox.com/0c/23/2WLDbV5Z_o.jpg",
          "https://images2.imgbox.com/1e/7e/9G5uuxYk_o.jpg",
          "https://images2.imgbox.com/bf/c2/Vcwe39A1_o.jpg",
          "https://images2.imgbox.com/b4/a5/mQR0ksFq_o.jpg",
          "https://images2.imgbox.com/eb/46/W4NPBtDl_o.jpg",
          "https://images2.imgbox.com/67/09/o3JUJURB_o.jpg",
          "https://images2.imgbox.com/42/d2/B8JcDNJT_o.jpg",
          "https://images2.imgbox.com/4d/b2/0a4U8zx6_o.jpg",
          "https://images2.imgbox.com/7e/37/a1H3C1kD_o.jpg",
          "https://images2.imgbox.com/19/ac/2xKfSIrc_o.jpg",
          "https://images2.imgbox.com/5e/69/X0uE8I3S_o.jpg",
          "https://images2.imgbox.com/58/a4/mEyYFWEQ_o.jpg",
          "https://images2.imgbox.com/bc/c3/mjHoNt3o_o.jpg",
          "https://images2.imgbox.com/e9/c0/bKJfcyHT_o.jpg",
          "https://images2.imgbox.com/f3/61/sWFFTE4r_o.jpg",
          "https://images2.imgbox.com/bc/b2/nzOFQKvo_o.jpg",
          "https://images2.imgbox.com/a6/ba/5ZrGPY6g_o.jpg",
          "https://images2.imgbox.com/0d/2e/CcZI7za0_o.jpg",
          "https://images2.imgbox.com/5b/78/IOTp67nE_o.jpg"
        ]
      }
    },
    "9": {
      "title": "Capítulo 09",
      "groups": {
        "Valkyriescan": [
          "https://images2.imgbox.com/ca/89/d3XuSzOC_o.jpg",
          "https://images2.imgbox.com/75/aa/xRc7vCeg_o.jpg",
          "https://images2.imgbox.com/6e/74/RYJppfkb_o.jpg",
          "https://images2.imgbox.com/d8/83/ZJRriErW_o.jpg",
          "https://images2.imgbox.com/9b/5c/x8JQWKNE_o.jpg",
          "https://images2.imgbox.com/88/2a/ocU8xowk_o.jpg",
          "https://images2.imgbox.com/32/ec/UZgoA0TW_o.jpg",
          "https://images2.imgbox.com/8f/7c/sFypNsIf_o.jpg",
          "https://images2.imgbox.com/66/e7/zitH1TPI_o.jpg",
          "https://images2.imgbox.com/b2/b7/lUkMiOOR_o.jpg",
          "https://images2.imgbox.com/24/63/JnIkZgij_o.jpg",
          "https://images2.imgbox.com/71/76/enETFbRE_o.jpg",
          "https://images2.imgbox.com/5c/71/Qiy6XEUr_o.jpg",
          "https://images2.imgbox.com/a9/fa/JgUioHzn_o.jpg",
          "https://images2.imgbox.com/0d/e4/heM2Qx4c_o.jpg",
          "https://images2.imgbox.com/68/2f/PAW6NdO9_o.jpg",
          "https://images2.imgbox.com/08/32/LsgFLt2v_o.jpg",
          "https://images2.imgbox.com/3e/e1/HMWu8JHO_o.jpg",
          "https://images2.imgbox.com/c0/43/kkoQWBBi_o.jpg",
          "https://images2.imgbox.com/b0/cd/R2ENvlcX_o.jpg",
          "https://images2.imgbox.com/26/5f/N5IzrE25_o.jpg",
          "https://images2.imgbox.com/ca/b2/2SQJmx2q_o.jpg",
          "https://images2.imgbox.com/89/ea/0YbF7Vyx_o.jpg",
          "https://images2.imgbox.com/71/f4/pN86SWkQ_o.jpg",
          "https://images2.imgbox.com/51/fa/jpOAerEB_o.jpg",
          "https://images2.imgbox.com/20/83/e1CJwhjD_o.jpg",
          "https://images2.imgbox.com/ce/be/dj2kBaV3_o.jpg",
          "https://images2.imgbox.com/ab/24/gmnC8F4p_o.jpg",
          "https://images2.imgbox.com/4b/4e/gJKtjeiv_o.jpg"
        ]
      }
    },
    "8": {
      "title": "Capítulo 08",
      "groups": {
        "Valkyriescan": [
          "https://images2.imgbox.com/4f/90/0o5WZbLW_o.jpg",
          "https://images2.imgbox.com/27/e3/51ZYgEUR_o.jpg",
          "https://images2.imgbox.com/11/a4/pt4OV2Nv_o.jpg",
          "https://images2.imgbox.com/4e/6d/awZMOt23_o.jpg",
          "https://images2.imgbox.com/b7/0b/sIHUV9MF_o.jpg",
          "https://images2.imgbox.com/36/18/OOsuj5P7_o.jpg",
          "https://images2.imgbox.com/a3/2c/0Aeclsh4_o.jpg",
          "https://images2.imgbox.com/a2/e4/1eBNos4e_o.jpg",
          "https://images2.imgbox.com/39/93/6CmJ7bMe_o.jpg",
          "https://images2.imgbox.com/b3/c3/n9qsO0iG_o.jpg",
          "https://images2.imgbox.com/45/a4/BjtmHCA2_o.jpg",
          "https://images2.imgbox.com/e0/b3/0GZwi6T6_o.jpg",
          "https://images2.imgbox.com/6c/ba/YTdz14zo_o.jpg",
          "https://images2.imgbox.com/26/d2/Gzvcoj3Z_o.jpg",
          "https://images2.imgbox.com/bf/c9/Y5nkvoTW_o.jpg",
          "https://images2.imgbox.com/27/6b/xubfdXi4_o.jpg",
          "https://images2.imgbox.com/eb/de/S0r3xJ6w_o.jpg",
          "https://images2.imgbox.com/61/32/MtHK4wyr_o.jpg",
          "https://images2.imgbox.com/1f/82/EA6Lo15A_o.jpg",
          "https://images2.imgbox.com/1b/72/bOEhg0r7_o.jpg",
          "https://images2.imgbox.com/9a/ae/JM44JtFX_o.jpg",
          "https://images2.imgbox.com/66/1c/4U9703I5_o.jpg",
          "https://images2.imgbox.com/f3/1b/CN7jnain_o.jpg",
          "https://images2.imgbox.com/48/af/XQXtVzxv_o.jpg",
          "https://images2.imgbox.com/e1/7c/xyMBbAPv_o.jpg"
        ]
      }
    },
    "7": {
      "title": "Capítulo 07",
      "groups": {
        "Valkyriescan": [
          "https://images2.imgbox.com/20/83/GxfLqhoU_o.jpg",
          "https://images2.imgbox.com/2e/2f/Pe3nVSEP_o.jpg",
          "https://images2.imgbox.com/41/60/ydYSC1Mg_o.jpg",
          "https://images2.imgbox.com/c6/4d/rJaYcpIv_o.jpg",
          "https://images2.imgbox.com/f5/96/2SmRdGza_o.jpg",
          "https://images2.imgbox.com/5a/3c/NsVjGeRg_o.jpg",
          "https://images2.imgbox.com/ba/32/uDqDtqOo_o.jpg",
          "https://images2.imgbox.com/5e/57/xLCkVi3j_o.jpg",
          "https://images2.imgbox.com/ea/77/b5bJNzRa_o.jpg",
          "https://images2.imgbox.com/fc/36/2HSml2Bg_o.jpg",
          "https://images2.imgbox.com/14/40/TRy6hTtJ_o.jpg",
          "https://images2.imgbox.com/a3/50/rkTOABDm_o.jpg",
          "https://images2.imgbox.com/20/b2/aRH4CU4I_o.jpg",
          "https://images2.imgbox.com/ea/26/WPcBi6gJ_o.jpg",
          "https://images2.imgbox.com/61/93/wwNJdJ4F_o.jpg",
          "https://images2.imgbox.com/b7/1d/f6T00H5J_o.jpg",
          "https://images2.imgbox.com/cf/aa/qbNVygoU_o.jpg",
          "https://images2.imgbox.com/bf/10/opDRYk4b_o.jpg",
          "https://images2.imgbox.com/2b/cb/BmoWf6Nh_o.jpg",
          "https://images2.imgbox.com/7d/9c/LPjYMTHD_o.jpg",
          "https://images2.imgbox.com/83/c0/A0wtpc0m_o.jpg",
          "https://images2.imgbox.com/b3/46/1WOzXEmK_o.jpg",
          "https://images2.imgbox.com/3d/72/W1AgsyId_o.jpg",
          "https://images2.imgbox.com/fd/4e/NLO49Qnh_o.jpg",
          "https://images2.imgbox.com/fa/34/yuNcmtaU_o.jpg",
          "https://images2.imgbox.com/2b/7d/gorRCcIs_o.jpg",
          "https://images2.imgbox.com/20/68/3iUz42nQ_o.jpg",
          "https://images2.imgbox.com/e5/cb/aDOMqMPh_o.jpg",
          "https://images2.imgbox.com/75/84/puXv51Ht_o.jpg",
          "https://images2.imgbox.com/9b/06/F0zEcYNG_o.jpg",
          "https://images2.imgbox.com/5f/f3/c2rmKjL9_o.jpg",
          "https://images2.imgbox.com/fa/a0/gfSmFJnx_o.jpg",
          "https://images2.imgbox.com/ca/47/wnnLJWLh_o.jpg",
          "https://images2.imgbox.com/69/30/wZjXyRBI_o.jpg",
          "https://images2.imgbox.com/f8/ca/677TRNUR_o.jpg",
          "https://images2.imgbox.com/81/b4/DJJf0qmJ_o.jpg",
          "https://images2.imgbox.com/e0/84/KF0s0RQX_o.jpg",
          "https://images2.imgbox.com/59/25/wsdQkmA6_o.jpg"
        ]
      }
    },
    "6.5": {
      "title": "Capítulo 6.5",
      "groups": {
        "Valkyriescan": [
          "https://images2.imgbox.com/da/00/aSwqy6fP_o.jpg",
          "https://images2.imgbox.com/28/8f/Nqj0SK7p_o.jpg",
          "https://images2.imgbox.com/5f/68/WIsswlf0_o.jpg",
          "https://images2.imgbox.com/78/da/KPYDGItK_o.jpg",
          "https://images2.imgbox.com/2a/40/bLyH2AYF_o.jpg",
          "https://images2.imgbox.com/18/35/Qv17j8tO_o.jpg",
          "https://images2.imgbox.com/13/ff/IBCYJH9P_o.jpg",
          "https://images2.imgbox.com/90/a1/SOxzcQbq_o.jpg",
          "https://images2.imgbox.com/9b/00/TIuX2PxK_o.jpg",
          "https://images2.imgbox.com/6a/9e/NgTegHdi_o.jpg",
          "https://images2.imgbox.com/fd/a4/ahxl9RLO_o.jpg",
          "https://images2.imgbox.com/56/10/yTa2lZvm_o.jpg"
        ]
      }
    },
    "6": {
      "title": "Capítulo 06",
      "groups": {
        "Valkyriescan": [
          "https://images2.imgbox.com/16/70/Nhw01cBu_o.jpg",
          "https://images2.imgbox.com/3d/9e/l6GSX6oL_o.jpg",
          "https://images2.imgbox.com/e4/38/Po7m4y5m_o.jpg",
          "https://images2.imgbox.com/27/30/azD2I6pD_o.jpg",
          "https://images2.imgbox.com/f6/6e/bcVjBbzf_o.jpg",
          "https://images2.imgbox.com/2a/2c/9PDXKwf2_o.jpg",
          "https://images2.imgbox.com/29/aa/Hna5ZKIn_o.jpg",
          "https://images2.imgbox.com/70/1f/5WE9zyUa_o.jpg",
          "https://images2.imgbox.com/69/7f/0JlxaLVn_o.jpg",
          "https://images2.imgbox.com/7f/5d/q6snswBJ_o.jpg",
          "https://images2.imgbox.com/58/44/Qp3z4H4c_o.jpg",
          "https://images2.imgbox.com/91/9e/xAoC9hFn_o.jpg",
          "https://images2.imgbox.com/7c/43/gYy6Jmmv_o.jpg",
          "https://images2.imgbox.com/a6/b9/GHpbYyiQ_o.jpg",
          "https://images2.imgbox.com/04/46/EX5ztDGI_o.jpg",
          "https://images2.imgbox.com/90/ad/rJ0Om9Wq_o.jpg",
          "https://images2.imgbox.com/45/b2/2MCXkuK4_o.jpg",
          "https://images2.imgbox.com/ff/74/qEPhx2zQ_o.jpg",
          "https://images2.imgbox.com/38/41/vbZrEGLN_o.jpg",
          "https://images2.imgbox.com/4b/b4/p7K6CgcK_o.jpg",
          "https://images2.imgbox.com/fa/16/3hTps6Lj_o.jpg",
          "https://images2.imgbox.com/a3/b8/lE5vJRep_o.jpg",
          "https://images2.imgbox.com/04/09/Mus87tSx_o.jpg",
          "https://images2.imgbox.com/d1/da/Q4sRZaay_o.jpg",
          "https://images2.imgbox.com/bd/70/9FMUuPzI_o.jpg"
        ]
      }
    },
    "5": {
      "title": "Capítulo 05",
      "groups": {
        "Valkyriescan": [
          "https://images2.imgbox.com/ca/24/reKEFQAK_o.jpg",
          "https://images2.imgbox.com/e5/2c/FaH7vGgA_o.jpg",
          "https://images2.imgbox.com/dd/e3/EMzxO89l_o.jpg",
          "https://images2.imgbox.com/1f/ff/GNkoghhs_o.jpg",
          "https://images2.imgbox.com/7b/54/ljbIYwXx_o.jpg",
          "https://images2.imgbox.com/d1/1a/aQ3Q9xa3_o.jpg",
          "https://images2.imgbox.com/25/3a/oCpWhWTx_o.jpg",
          "https://images2.imgbox.com/6b/af/ojLhnTmz_o.jpg",
          "https://images2.imgbox.com/64/be/UenmnOJP_o.jpg",
          "https://images2.imgbox.com/7c/3b/h4sDjuep_o.jpg",
          "https://images2.imgbox.com/15/4e/ok1rt1oA_o.jpg",
          "https://images2.imgbox.com/74/25/0CyM54nX_o.jpg",
          "https://images2.imgbox.com/46/09/QiUsphiD_o.jpg",
          "https://images2.imgbox.com/dd/b3/BAAySE2w_o.jpg",
          "https://images2.imgbox.com/34/e1/aoHENM6K_o.jpg",
          "https://images2.imgbox.com/d1/27/kBX9152E_o.jpg",
          "https://images2.imgbox.com/82/b7/ZJ5C40ip_o.jpg",
          "https://images2.imgbox.com/01/47/lERIpckg_o.jpg",
          "https://images2.imgbox.com/e8/eb/PAAOVuwl_o.jpg",
          "https://images2.imgbox.com/59/64/wUH15WiK_o.jpg",
          "https://images2.imgbox.com/a8/9f/IFgOsj34_o.jpg",
          "https://images2.imgbox.com/85/c8/Ta5DmBJF_o.jpg",
          "https://images2.imgbox.com/70/aa/WMkAnQPn_o.jpg",
          "https://images2.imgbox.com/1d/87/0v7ELWuU_o.jpg"
        ]
      }
    },
    "4": {
      "title": "Capítulo 04",
      "groups": {
        "Valkyriescan": [
          "https://images2.imgbox.com/82/2f/DVxE2HOI_o.jpg",
          "https://images2.imgbox.com/98/6d/snvOGMzZ_o.jpg",
          "https://images2.imgbox.com/36/ca/6dHlYzhR_o.jpg",
          "https://images2.imgbox.com/4a/4c/n7MWWWvH_o.jpg",
          "https://images2.imgbox.com/d5/06/HleQV2YW_o.jpg",
          "https://images2.imgbox.com/48/71/6AGnPHA6_o.jpg",
          "https://images2.imgbox.com/69/27/KoeHiHH9_o.jpg",
          "https://images2.imgbox.com/9a/64/hAUR4718_o.jpg",
          "https://images2.imgbox.com/83/8b/WKisSkZG_o.jpg",
          "https://images2.imgbox.com/75/cc/pR1ZbqBS_o.jpg",
          "https://images2.imgbox.com/af/4a/pxPX3CV8_o.jpg",
          "https://images2.imgbox.com/b6/9f/UJEnlT7k_o.jpg",
          "https://images2.imgbox.com/d7/a7/SLGgyXv7_o.jpg",
          "https://images2.imgbox.com/e7/e0/hLQErxxh_o.jpg",
          "https://images2.imgbox.com/e7/82/iLoylGAW_o.jpg",
          "https://images2.imgbox.com/49/18/NrdzyjFN_o.jpg",
          "https://images2.imgbox.com/03/f1/tKcwGzNx_o.jpg",
          "https://images2.imgbox.com/7d/86/cGwNCS6s_o.jpg",
          "https://images2.imgbox.com/58/df/UH7oMfHb_o.jpg",
          "https://images2.imgbox.com/bc/68/ifXXEad5_o.jpg",
          "https://images2.imgbox.com/4b/ee/Vn4tuWO8_o.jpg",
          "https://images2.imgbox.com/bb/22/gxe1S45k_o.jpg",
          "https://images2.imgbox.com/68/89/DjB0wKch_o.jpg",
          "https://images2.imgbox.com/1c/cc/6At5JR2D_o.jpg",
          "https://images2.imgbox.com/d6/c6/hL2TsXsh_o.jpg"
        ]
      }
    },
    "3": {
      "title": "Capítulo 03",
      "groups": {
        "Valkyriescan": [
          "https://images2.imgbox.com/77/8c/qKTomuYr_o.jpg",
          "https://images2.imgbox.com/9c/32/XHdTHoI0_o.jpg",
          "https://images2.imgbox.com/55/92/hNk8TdtH_o.jpg",
          "https://images2.imgbox.com/12/46/TTHiLZC1_o.jpg",
          "https://images2.imgbox.com/07/fb/KXIsZUwS_o.jpg",
          "https://images2.imgbox.com/57/6a/Us1RGP0S_o.jpg",
          "https://images2.imgbox.com/bf/ff/96OCucPW_o.jpg",
          "https://images2.imgbox.com/15/3d/TQZXZ0VB_o.jpg",
          "https://images2.imgbox.com/1d/74/sGWflt0i_o.jpg",
          "https://images2.imgbox.com/f6/54/2Mmh2YHf_o.jpg",
          "https://images2.imgbox.com/48/d6/b0eFXnSf_o.jpg",
          "https://images2.imgbox.com/85/3e/fJTbLrfT_o.jpg",
          "https://images2.imgbox.com/2a/43/lybcbVAP_o.jpg",
          "https://images2.imgbox.com/c6/2b/f2YAH1hD_o.jpg",
          "https://images2.imgbox.com/57/b0/Bg7qxZSO_o.jpg",
          "https://images2.imgbox.com/16/ad/F1RnUDgx_o.jpg",
          "https://images2.imgbox.com/bb/c2/1jXMhcjE_o.jpg",
          "https://images2.imgbox.com/fe/b6/ycK2BI9e_o.jpg",
          "https://images2.imgbox.com/18/fc/vU55wM64_o.jpg",
          "https://images2.imgbox.com/37/b7/GssIcCPV_o.jpg",
          "https://images2.imgbox.com/eb/05/QWOk1y2n_o.jpg",
          "https://images2.imgbox.com/0b/23/roQQhpEG_o.jpg",
          "https://images2.imgbox.com/4a/b3/0n0Mhult_o.jpg",
          "https://images2.imgbox.com/cd/17/hArXarGq_o.jpg",
          "https://images2.imgbox.com/b3/f1/wnekhGTI_o.jpg"
        ]
      }
    },
    "2": {
      "title": "Capítulo 02",
      "groups": {
        "Valkyriescan": [
          "https://images2.imgbox.com/11/4e/Y4jpwOAc_o.png",
          "https://images2.imgbox.com/13/f1/j0UWzJ42_o.jpg",
          "https://images2.imgbox.com/a0/b1/b5tFVTOP_o.jpg",
          "https://images2.imgbox.com/6b/00/FLF1WSuX_o.jpg",
          "https://images2.imgbox.com/ba/ef/p4BLNwrS_o.jpg",
          "https://images2.imgbox.com/87/5f/wHCyD7Sc_o.jpg",
          "https://images2.imgbox.com/83/43/ko7v4Sz5_o.jpg",
          "https://images2.imgbox.com/de/7b/PZ1kGhmJ_o.jpg",
          "https://images2.imgbox.com/09/83/m7HavMTx_o.jpg",
          "https://images2.imgbox.com/2a/2b/4N0fXwfb_o.jpg",
          "https://images2.imgbox.com/7b/20/BUi9tZye_o.jpg",
          "https://images2.imgbox.com/78/6a/aaZt9a1I_o.jpg",
          "https://images2.imgbox.com/03/b5/Ey5MdAEg_o.jpg",
          "https://images2.imgbox.com/cd/c7/wdaGgLjZ_o.jpg",
          "https://images2.imgbox.com/bf/34/VuBNXSYk_o.jpg",
          "https://images2.imgbox.com/7d/42/QhK4zEh0_o.jpg",
          "https://images2.imgbox.com/83/4a/c8GuqQyl_o.jpg",
          "https://images2.imgbox.com/22/53/dt6s3OTs_o.jpg",
          "https://images2.imgbox.com/1c/ea/c2gpfYBl_o.jpg",
          "https://images2.imgbox.com/e9/99/NjP5It2F_o.jpg",
          "https://images2.imgbox.com/32/c0/XfuXOxII_o.jpg",
          "https://images2.imgbox.com/2e/ce/t2AKGicL_o.jpg",
          "https://images2.imgbox.com/6c/f7/s8hWa9h1_o.jpg",
          "https://images2.imgbox.com/69/a9/HIRWpvR0_o.jpg",
          "https://images2.imgbox.com/c0/d6/5lkA31eh_o.jpg"
        ]
      }
    },
    "1": {
      "title": "Capítulo 01",
      "groups": {
        "Valkyriescan": [
          "https://images2.imgbox.com/72/95/GWNJwtcx_o.png",
          "https://images2.imgbox.com/5b/83/UKUehWRC_o.png",
          "https://images2.imgbox.com/45/f9/1GxVLzja_o.png",
          "https://images2.imgbox.com/12/3f/Yw4Uvosa_o.png",
          "https://images2.imgbox.com/94/7f/4HHMPTPY_o.png",
          "https://images2.imgbox.com/9c/8a/HZJB8Pb9_o.png",
          "https://images2.imgbox.com/35/f6/KyyStOvP_o.png",
          "https://images2.imgbox.com/2b/a7/mrlqxuW4_o.png",
          "https://images2.imgbox.com/0e/e8/viK2GOvQ_o.png",
          "https://images2.imgbox.com/06/33/ryDVXcTn_o.png",
          "https://images2.imgbox.com/7d/8d/PK8sHLY4_o.png",
          "https://images2.imgbox.com/42/66/8X0j3jx7_o.png",
          "https://images2.imgbox.com/70/1a/QFH1ihto_o.png",
          "https://images2.imgbox.com/eb/6e/aCTJk5Pu_o.png",
          "https://images2.imgbox.com/e8/1a/wWqMlXLU_o.png",
          "https://images2.imgbox.com/ee/8c/X4aT6i47_o.png",
          "https://images2.imgbox.com/02/c4/vpDSk4Lk_o.png",
          "https://images2.imgbox.com/62/63/3E59Bbsz_o.png",
          "https://images2.imgbox.com/5b/89/j2OCGNGs_o.png",
          "https://images2.imgbox.com/5b/20/NqDFlRlU_o.png",
          "https://images2.imgbox.com/8a/02/KNMGEt4o_o.png",
          "https://images2.imgbox.com/53/4d/2pnP8j3y_o.png",
          "https://images2.imgbox.com/b3/07/eYsU3k9X_o.png",
          "https://images2.imgbox.com/47/b4/j7N9rydA_o.png",
          "https://images2.imgbox.com/14/ec/9FVNOvMO_o.png",
          "https://images2.imgbox.com/3a/79/3C5oCmj3_o.png",
          "https://images2.imgbox.com/04/0a/HHPwFYoc_o.png",
          "https://images2.imgbox.com/4f/7a/Y0RGhE4F_o.png",
          "https://images2.imgbox.com/60/64/Mn3272N6_o.png",
          "https://images2.imgbox.com/ba/c8/fHtkGcp8_o.png",
          "https://images2.imgbox.com/ae/fc/rPHrC6QW_o.png",
          "https://images2.imgbox.com/c5/08/u4MV25d2_o.png",
          "https://images2.imgbox.com/53/fe/tTT9iOdr_o.png",
          "https://images2.imgbox.com/fc/53/SnzuwHYP_o.png",
          "https://images2.imgbox.com/da/fd/GY1gTf1e_o.png",
          "https://images2.imgbox.com/e1/04/GKxvryQL_o.png",
          "https://images2.imgbox.com/c0/c5/00P7yv8y_o.png",
          "https://images2.imgbox.com/d7/8a/LVoQtWG2_o.png"
        ]
      }
    }
  }
}