{
  "title": "Julia in the box!",
  "author": "Aotsubaki Toto",
  "artist": "Aotsubaki Toto",
  "description": "Maki, uma universitária, tem passado os dias sendo levada por Julia, uma moça de família rica e protegida, para lugares mais populares, a pedido dela. Um dia, Julia disse que queria ir a um cassino…",
  "cover": "https://images2.imgbox.com/12/a1/VvtQUhMr_o.jpg",
  "status": "Completo",
  "chapters": {
    "0": {
      "title": "Capítulo único",
      "groups": {
        "Valkyriescan": [
          "https://images2.imgbox.com/89/87/x2kXbdit_o.png",
          "https://images2.imgbox.com/f1/91/FA8l6kC9_o.jpg",
          "https://images2.imgbox.com/b9/f3/mga1cROq_o.jpg",
          "https://images2.imgbox.com/a3/d2/jyADFdeP_o.jpg",
          "https://images2.imgbox.com/06/cb/G5QRJaV7_o.jpg",
          "https://images2.imgbox.com/c0/3c/jjGdxjYW_o.jpg",
          "https://images2.imgbox.com/40/78/UtMJtC3o_o.jpg",
          "https://images2.imgbox.com/b5/6b/Xwqc9Zz8_o.jpg",
          "https://images2.imgbox.com/52/03/9h5296vm_o.jpg",
          "https://images2.imgbox.com/c9/ca/7XSUsDQD_o.jpg",
          "https://images2.imgbox.com/5d/94/RGi39Cmk_o.jpg",
          "https://images2.imgbox.com/0e/9b/r9bBbDgx_o.jpg",
          "https://images2.imgbox.com/7d/b1/KOIJmkg7_o.jpg",
          "https://images2.imgbox.com/a7/1c/Dqk15CnZ_o.jpg",
          "https://images2.imgbox.com/bf/6c/BpHtSFnX_o.jpg",
          "https://images2.imgbox.com/08/fd/dgVIRi9P_o.jpg",
          "https://images2.imgbox.com/84/5b/ZSwsXIgy_o.jpg",
          "https://images2.imgbox.com/2c/7a/l239LbJ8_o.jpg",
          "https://images2.imgbox.com/f7/9a/2ZhhKASY_o.jpg",
          "https://images2.imgbox.com/a3/39/ka7khY1K_o.jpg",
          "https://images2.imgbox.com/69/94/xFz7x1WH_o.jpg",
          "https://images2.imgbox.com/9b/b5/MWsTOKAq_o.jpg",
          "https://images2.imgbox.com/40/2f/OP9KGyTy_o.jpg",
          "https://images2.imgbox.com/63/2a/024be8XX_o.jpg",
          "https://images2.imgbox.com/a3/36/Z1QDNSal_o.jpg",
          "https://images2.imgbox.com/47/9a/mtRNgcJ6_o.jpg"
        ]
      }
    }
  }
}